Workbook

Sheet M&A
A1: DEAL ID | B1: Announcement date | C1: rank date | D1: rank value inc. net cdebt target (USD , MILLIONS) | E1: TARGET COMPANY | F1: TARGET MACRO INDUSTRY | G1: TARGET MID INDUSTRY | H1: TARGET NATION | I1: ACQUIROR FULL NAME | J1: ACQUIROR MACRO INDUSTRY | K1: ACQUIROR MID INDUSTRY | L1: ACQUIROR NATION | M1: TARGET FINANCIAL ADVISOR NAME | N1: ACQUIROR FINANCIAL ADVISOR NAME | O1: DEAL STATUS | P1: NATION CLASSIFICATION | Q1: M &A TYPE | R1: TARGET STOCK EXCHANGE NAME | S1: premium paid 1 day prior to announcement | T1: premium paid 1 week prior to announcement | U1: premium paid 4 weeks prior to announcement | V1: PREMIUM STATUS | W1: DATE ANNOUNCED | X1: YEAR | Y1: Helper | Z1: Helper | AA1: RULE OF LAW | AB1: Political Risk | AC1: Government Effectiveness | AD1: Credit Rating | AE1: CREDIT SCORE
A2: 2688229040 | B2: Wed Jan 01 2014 00:00:00 GMT+0000 (Greenwich Mean Time) | C2: Wed Jan 01 2014 00:00:00 GMT+0000 (Greenwich Mean Time) | D2: 142.45833 | E2: Hainan Jinhaisheng Investment Co Ltd | F2: Real Estate | G2: Other Real Estate | H2: China (Mainland) | I2: Guangzhou Junsi Architectural Design Co Ltd | J2: Industrials | K2: Building/Construction & Engineering | L2: China (Mainland) | N2: ICBC | O2: Completed | P2: China (Mainland) | Q2: Disclosed Dollar Value Deal | V2: =IF(ISNUMBER(S2), "Keep", "Remove") -> Remove
A3: 2688148040 | B3: Wed Jan 01 2014 00:00:00 GMT+0000 (Greenwich Mean Time) | C3: Wed Jan 01 2014 00:00:00 GMT+0000 (Greenwich Mean Time) | D3: 495.5647 | E3: Nanjing Fucheng Real Estate Development Co Ltd | F3: Real Estate | G3: Other Real Estate | H3: China (Mainland) | I3: Sanpower Group Co Ltd | J3: High Technology | K3: Computers & Peripherals | L3: China (Mainland) | N3: ICBC | O3: Completed | P3: China (Mainland) | Q3: Disclosed Dollar Value Deal | V3: =IF(ISNUMBER(S3), "Keep", "Remove") -> Remove
A4: 2598585040 | B4: Thu Jan 02 2014 00:00:00 GMT+0000 (Greenwich Mean Time) | C4: Mon Jun 16 2014 00:00:00 GMT+0100 (British Summer Time) | D4: 96.385542 | E4: Dalian Hissen Bio-Pharm Inc | F4: Healthcare | G4: Biotechnology | H4: China (Mainland) | I4: Meihua Holdings Group Co Ltd | J4: Healthcare | K4: Biotechnology | L4: China (Mainland) | O4: Completed | P4: China (Mainland) | Q4: Disclosed Dollar Value Deal | V4: =IF(ISNUMBER(S4), "Keep", "Remove") -> Remove
A5: 2598967040 | B5: Mon Jan 06 2014 00:00:00 GMT+0000 (Greenwich Mean Time) | C5: Mon Jan 06 2014 00:00:00 GMT+0000 (Greenwich Mean Time) | D5: 62.233164 | E5: Yashili(Zhengzhou)Nourishment Co Ltd | F5: Consumer Staples | G5: Food and Beverage | H5: China (Mainland) | I5: Investor Group | J5: Financials | K5: Other Financials | L5: Hong Kong | M5: Somerley Ltd | O5: Completed | P5: China (Mainland) | Q5: Disclosed Dollar Value Deal | V5: =IF(ISNUMBER(S5), "Keep", "Remove") -> Remove
A6: 2698127040 | B6: Tue Jan 07 2014 00:00:00 GMT+0000 (Greenwich Mean Time) | C6: Tue Jan 07 2014 00:00:00 GMT+0000 (Greenwich Mean Time) | D6: 148.74312 | E6: Guangzhou Hanchang Investment Advisory Co Ltd | F6: Real Estate | G6: Other Real Estate | H6: China (Mainland) | I6: Guangzhou Maode Investment Co Ltd | J6: Financials | K6: Other Financials | L6: China (Mainland) | N6: ICBC | O6: Completed | P6: China (Mainland) | Q6: Disclosed Dollar Value Deal | V6: =IF(ISNUMBER(S6), "Keep", "Remove") -> Remove
A7: 2687755040 | B7: Tue Jan 07 2014 00:00:00 GMT+0000 (Greenwich Mean Time) | C7: Tue Jan 07 2014 00:00:00 GMT+0000 (Greenwich Mean Time) | D7: 165.27013 | E7: Zhuhai International Shipping Co Ltd | F7: Industrials | G7: Transportation & Infrastructure | H7: China (Mainland) | I7: Shenzhen Weikangde Investment Group Co Ltd | J7: Financials | K7: Other Financials | L7: China (Mainland) | N7: ICBC | O7: Completed | P7: China (Mainland) | Q7: Disclosed Dollar Value Deal | V7: =IF(ISNUMBER(S7), "Keep", "Remove") -> Remove
A8: 2602068040 | B8: Sat Jan 11 2014 00:00:00 GMT+0000 (Greenwich Mean Time) | C8: Sat Jan 11 2014 00:00:00 GMT+0000 (Greenwich Mean Time) | D8: 160.28024 | E8: Shanghai Environment Group Co Ltd | F8: Government and Agencies | G8: Public Administration | H8: China (Mainland) | I8: Shanghai SMI Holding Co Ltd | J8: Energy and Power | K8: Water and Waste Management | L8: China (Mainland) | M8: Macquarie Group | O8: Completed | P8: China (Mainland) | Q8: Disclosed Dollar Value Deal | V8: =IF(ISNUMBER(S8), "Keep", "Remove") -> Remove
A9: 2687832040 | B9: Mon Jan 13 2014 00:00:00 GMT+0000 (Greenwich Mean Time) | C9: Mon Jan 13 2014 00:00:00 GMT+0000 (Greenwich Mean Time) | D9: 87.361001 | E9: Ningbo Qianhu International Meeting Centre Development Co Ltd | F9: Real Estate | G9: Other Real Estate | H9: China (Mainland) | I9: Ningbo Dongqian Lake Jingfu Tourism Investment Co Ltd | J9: Financials | K9: Other Financials | L9: China (Mainland) | N9: ICBC | O9: Completed | P9: China (Mainland) | Q9: Disclosed Dollar Value Deal | V9: =IF(ISNUMBER(S9), "Keep", "Remove") -> Remove
A10: 2601793040 | B10: Mon Jan 13 2014 00:00:00 GMT+0000 (Greenwich Mean Time) | C10: Mon Feb 24 2014 00:00:00 GMT+0000 (Greenwich Mean Time) | D10: 5528.0004 | E10: ALL America Latina Logistica SA | F10: Industrials | G10: Transportation & Infrastructure | H10: Brazil | I10: Rumo Logistica Operadora Multimodal SA | J10: Industrials | K10: Transportation & Infrastructure | L10: Brazil | M10: Estater Gestao e Financas|Santander Corp & Invest Bkg|Bradesco BBI|Brasil Plural SA | N10: Rothschild & Co|Credit Suisse Group|Banco Itau-BBA SA|Banco BTG Pactual SA | O10: Completed | P10: Brazil | Q10: Disclosed Dollar Value Deal | R10: BMFBOVESPA | V10: =IF(ISNUMBER(S10), "Keep", "Remove") -> Remove
A11: 2601249040 | B11: Tue Jan 14 2014 00:00:00 GMT+0000 (Greenwich Mean Time) | C11: Tue Jan 14 2014 00:00:00 GMT+0000 (Greenwich Mean Time) | D11: 423.49939 | E11: Beijing Tianshen Interactive Technology Co Ltd | F11: High Technology | G11: Internet Software & Services | H11: China (Mainland) | I11: Dalian Kemian Wood Industry Co Ltd | J11: Industrials | K11: Other Industrials | L11: China (Mainland) | N11: China Securities Co Ltd | O11: Completed | P11: China (Mainland) | Q11: Disclosed Dollar Value Deal | V11: =IF(ISNUMBER(S11), "Keep", "Remove") -> Remove
A12: 2601575040 | B12: Wed Jan 15 2014 00:00:00 GMT+0000 (Greenwich Mean Time) | C12: Wed Jan 15 2014 00:00:00 GMT+0000 (Greenwich Mean Time) | D12: 156.80848 | E12: Shenzhen Wangxin Precision Industry Co Ltd | F12: Consumer Products and Services | G12: Home Furnishings | H12: China (Mainland) | I12: Beijing IRTOUCH Systems Co Ltd | J12: High Technology | K12: Electronics | L12: China (Mainland) | N12: GF Securities | O12: Completed | P12: China (Mainland) | Q12: Disclosed Dollar Value Deal | V12: =IF(ISNUMBER(S12), "Keep", "Remove") -> Remove
A13: 2602459040 | B13: Thu Jan 16 2014 00:00:00 GMT+0000 (Greenwich Mean Time) | C13: Thu May 15 2014 00:00:00 GMT+0100 (British Summer Time) | D13: 261.61799 | E13: Shanghai Jinqiao Export Processing Zone United Development Co Ltd | F13: Financials | G13: Other Financials | H13: China (Mainland) | I13: Shanghai Jinqiao Export Processing Zone Development Co Ltd | J13: Real Estate | K13: Other Real Estate | L13: China (Mainland) | O13: Completed | P13: China (Mainland) | Q13: Disclosed Dollar Value Deal | V13: =IF(ISNUMBER(S13), "Keep", "Remove") -> Remove
A14: 2602016040 | B14: Thu Jan 16 2014 00:00:00 GMT+0000 (Greenwich Mean Time) | C14: Thu Jan 16 2014 00:00:00 GMT+0000 (Greenwich Mean Time) | D14: 331.58748 | E14: Jilong Ruimei Information Consulting Co Ltd | F14: Financials | G14: Asset Management | H14: China (Mainland) | I14: Shanghai Hyron Software Co Ltd | J14: High Technology | K14: IT Consulting & Services | L14: China (Mainland) | N14: Soochow Securities Co Ltd | O14: Completed | P14: China (Mainland) | Q14: Disclosed Dollar Value Deal | V14: =IF(ISNUMBER(S14), "Keep", "Remove") -> Remove
A15: 2601996040 | B15: Thu Jan 16 2014 00:00:00 GMT+0000 (Greenwich Mean Time) | C15: Thu Jan 16 2014 00:00:00 GMT+0000 (Greenwich Mean Time) | D15: 453.5613 | E15: Jilong Ruixin Investment Co Ltd | F15: Financials | G15: Other Financials | H15: China (Mainland) | I15: Shanghai Hyron Software Co Ltd | J15: High Technology | K15: IT Consulting & Services | L15: China (Mainland) | N15: Soochow Securities Co Ltd | O15: Completed | P15: China (Mainland) | Q15: Disclosed Dollar Value Deal | V15: =IF(ISNUMBER(S15), "Keep", "Remove") -> Remove
A16: 2604837040 | B16: Fri Jan 17 2014 00:00:00 GMT+0000 (Greenwich Mean Time) | C16: Fri Jan 17 2014 00:00:00 GMT+0000 (Greenwich Mean Time) | D16: 226.5438 | E16: Daikin Industries&Electronics Equipment(Suzhou)Co Ltd | F16: Industrials | G16: Machinery | H16: China (Mainland) | I16: Daikin China Investment Co Ltd | J16: Industrials | K16: Machinery | L16: China (Mainland) | O16: Completed | P16: China (Mainland) | Q16: Disclosed Dollar Value Deal | V16: =IF(ISNUMBER(S16), "Keep", "Remove") -> Remove
A17: 2603196040 | B17: Fri Jan 17 2014 00:00:00 GMT+0000 (Greenwich Mean Time) | C17: Sat Jan 25 2014 00:00:00 GMT+0000 (Greenwich Mean Time) | D17: 196.72271 | E17: Hubei Taisheng Chemical Co Ltd | F17: Materials | G17: Chemicals | H17: China (Mainland) | I17: Hubei Xingfa Chemicals Group Co Ltd | J17: Materials | K17: Chemicals | L17: China (Mainland) | N17: Changjiang Financing Services | O17: Completed | P17: China (Mainland) | Q17: Disclosed Dollar Value Deal | V17: =IF(ISNUMBER(S17), "Keep", "Remove") -> Remove
A18: 2602796040 | B18: Fri Jan 17 2014 00:00:00 GMT+0000 (Greenwich Mean Time) | C18: Fri Jan 17 2014 00:00:00 GMT+0000 (Greenwich Mean Time) | D18: 96.694215 | E18: Hillview Golf Development Co Ltd | F18: Consumer Products and Services | G18: Travel Services | H18: China (Mainland) | I18: San Tai Investment Co Ltd | J18: Media and Entertainment | K18: Advertising & Marketing | L18: Hong Kong | N18: Deloitte & Touche Corp Finance|Goldin Financial Holdings Ltd | O18: Completed | P18: China (Mainland) | Q18: Disclosed Dollar Value Deal | V18: =IF(ISNUMBER(S18), "Keep", "Remove") -> Remove
A19: 2602499040 | B19: Fri Jan 17 2014 00:00:00 GMT+0000 (Greenwich Mean Time) | C19: Fri Jan 17 2014 00:00:00 GMT+0000 (Greenwich Mean Time) | D19: 148.76033 | E19: Chongqing Orchard Container Terminal Co Ltd | F19: Industrials | G19: Transportation & Infrastructure | H19: China (Mainland) | I19: Chongqing Gangjiu Co Ltd | J19: Industrials | K19: Transportation & Infrastructure | L19: China (Mainland) | O19: Completed | P19: China (Mainland) | Q19: Disclosed Dollar Value Deal | V19: =IF(ISNUMBER(S19), "Keep", "Remove") -> Remove
A20: 2602432040 | B20: Fri Jan 17 2014 00:00:00 GMT+0000 (Greenwich Mean Time) | C20: Fri Jan 17 2014 00:00:00 GMT+0000 (Greenwich Mean Time) | D20: 140.51138 | E20: Beijing Guodu Internet Technology Co Ltd | F20: High Technology | G20: Software | H20: China (Mainland) | I20: Jiangsu Wutong Communications Co Ltd | J20: Telecommunications | K20: Telecommunications Equipment | L20: China (Mainland) | N20: Southwest Securities Co Ltd | O20: Completed | P20: China (Mainland) | Q20: Disclosed Dollar Value Deal | V20: =IF(ISNUMBER(S20), "Keep", "Remove") -> Remove
A21: 2709067040 | B21: Mon Jan 20 2014 00:00:00 GMT+0000 (Greenwich Mean Time) | C21: Mon Jan 20 2014 00:00:00 GMT+0000 (Greenwich Mean Time) | D21: 115.38967 | E21: Wuhan Zhongcheng Shenghai Property Co Ltd | F21: Real Estate | G21: Other Real Estate | H21: China (Mainland) | I21: Wuhan United Investments & Properties Co Ltd | J21: Real Estate | K21: Other Real Estate | L21: China (Mainland) | N21: ICBC | O21: Completed | P21: China (Mainland) | Q21: Disclosed Dollar Value Deal | V21: =IF(ISNUMBER(S21), "Keep", "Remove") -> Remove
A22: 2616639040 | B22: Mon Jan 20 2014 00:00:00 GMT+0000 (Greenwich Mean Time) | C22: Thu Mar 27 2014 00:00:00 GMT+0000 (Greenwich Mean Time) | D22: 52.230196 | E22: Reliance MediaWorks Ltd | F22: Media and Entertainment | G22: Motion Pictures / Audio Visual | H22: india | I22: Investor Group | J22: Financials | K22: Other Financials | L22: India | N22: ICICI Securities Ltd | O22: Completed | P22: India | Q22: Disclosed Dollar Value Deal | R22: National|Bombay | S22: 31.32 | T22: 27.88 | U22: 21.15 | V22: =IF(ISNUMBER(S22), "Keep", "Remove") -> Keep | W22: =MID(B22, 5, 11) -> Jan 20 2014 | X22: =VALUE(RIGHT(W22,4)) -> 2014 | Y22: =H22&X22 -> india2014 | Z22: india2014 | AA22: =IFERROR(VLOOKUP(Z22, RISKSHEET!$A$2:$G$1000, 4, FALSE), "Missing") -> -0.069189385 | AB22: =IFERROR(VLOOKUP(Z22, RISKSHEET!$A$2:$G$1000, 5, FALSE), "Missing") -> -0.99791199 | AC22: =IFERROR(VLOOKUP(Z22, RISKSHEET!$A$2:$G$1000, 6, FALSE), "Missing") -> -0.15735514 | AD22: =_xlfn.XLOOKUP(Z22, CREDITRATING!I:I, CREDITRATING!E:E, "Missing") -> BBB- | AE22: =_xlfn.XLOOKUP(Z22, CREDITRATING!I:I, CREDITRATING!F:F, "Missing") -> 10
A23: 2603086040 | B23: Tue Jan 21 2014 00:00:00 GMT+0000 (Greenwich Mean Time) | C23: Tue Jan 21 2014 00:00:00 GMT+0000 (Greenwich Mean Time) | D23: 55.613275 | E23: Yangzhou Guangshuo Information Industry Development Co Ltd | F23: Real Estate | G23: Other Real Estate | H23: China (Mainland) | I23: Yangzhou Guangjiang Asset Management Co Ltd | J23: Consumer Products and Services | K23: Professional Services | L23: China (Mainland) | O23: Completed | P23: China (Mainland) | Q23: Disclosed Dollar Value Deal | V23: =IF(ISNUMBER(S23), "Keep", "Remove") -> Remove
A24: 2603418040 | B24: Wed Jan 22 2014 00:00:00 GMT+0000 (Greenwich Mean Time) | C24: Wed Jan 22 2014 00:00:00 GMT+0000 (Greenwich Mean Time) | D24: 142.47257 | E24: Wuxi Qiku Networks Technology Co Ltd | F24: High Technology | G24: Software | H24: China (Mainland) | I24: Zhejiang Century Huatong Automotive Part Co Ltd | J24: Industrials | K24: Automobiles & Components | L24: China (Mainland) | N24: Haitong Securities Co Ltd | O24: Completed | P24: China (Mainland) | Q24: Disclosed Dollar Value Deal | V24: =IF(ISNUMBER(S24), "Keep", "Remove") -> Remove
A25: 2603413040 | B25: Wed Jan 22 2014 00:00:00 GMT+0000 (Greenwich Mean Time) | C25: Wed Jan 22 2014 00:00:00 GMT+0000 (Greenwich Mean Time) | D25: 159.23332 | E25: Shanghai Tianyou Software Co Ltd | F25: High Technology | G25: Software | H25: China (Mainland) | I25: Zhejiang Century Huatong Automotive Part Co Ltd | J25: Industrials | K25: Automobiles & Components | L25: China (Mainland) | N25: Haitong Securities Co Ltd | O25: Completed | P25: China (Mainland) | Q25: Disclosed Dollar Value Deal | V25: =IF(ISNUMBER(S25), "Keep", "Remove") -> Remove
A26: 2603365040 | B26: Wed Jan 22 2014 00:00:00 GMT+0000 (Greenwich Mean Time) | C26: Wed Jan 22 2014 00:00:00 GMT+0000 (Greenwich Mean Time) | D26: 66.797779 | E26: Jiangsu Xinguang Environment Engineering Co Ltd | F26: Materials | G26: Construction Materials | H26: China (Mainland) | I26: Changzhou Tiansheng New Materials Co Ltd | J26: Materials | K26: Containers & Packaging | L26: China (Mainland) | N26: GF Securities | O26: Completed | P26: China (Mainland) | Q26: Disclosed Dollar Value Deal | V26: =IF(ISNUMBER(S26), "Keep", "Remove") -> Remove
A27: 2430167040 | B27: Thu Jan 23 2014 00:00:00 GMT+0000 (Greenwich Mean Time) | C27: Thu Jan 23 2014 00:00:00 GMT+0000 (Greenwich Mean Time) | D27: 64.445258 | E27: OAO Arkhangel'skiy tralovyi flot | F27: Consumer Staples | G27: Agriculture & Livestock | H27: Russia | I27: OOO Virma | J27: Consumer Staples | K27: Agriculture & Livestock | L27: Russia | M27: Gazprombank | O27: Completed | P27: Russia | Q27: Disclosed Dollar Value Deal | V27: =IF(ISNUMBER(S27), "Keep", "Remove") -> Remove
A28: 2608207040 | B28: Fri Jan 24 2014 00:00:00 GMT+0000 (Greenwich Mean Time) | C28: Tue Jan 28 2014 00:00:00 GMT+0000 (Greenwich Mean Time) | D28: 122.99987 | E28: Nuomi Holdings Inc | F28: High Technology | G28: Computers & Peripherals | H28: China (Mainland) | I28: Baidu Holdings Ltd | J28: Financials | K28: Other Financials | L28: China (Mainland) | O28: Completed | P28: China (Mainland) | Q28: Disclosed Dollar Value Deal | V28: =IF(ISNUMBER(S28), "Keep", "Remove") -> Remove
A29: 2645899040 | B29: Mon Jan 27 2014 00:00:00 GMT+0000 (Greenwich Mean Time) | C29: Fri Jun 20 2014 00:00:00 GMT+0100 (British Summer Time) | D29: 110.02827 | E29: Cia Providencia Industria e Comercio | F29: Consumer Staples | G29: Textiles & Apparel | H29: Brazil | I29: PGI Polimeros do Brasil SA | J29: Consumer Staples | K29: Textiles & Apparel | L29: Brazil | M29: Lazard | N29: Barclays|Citi|Patria Investimentos|Itau Unibanco | O29: Completed | P29: Brazil | Q29: Disclosed Dollar Value Deal | R29: BMFBOVESPA | S29: 49.79 | T29: 43.11 | U29: 34.22 | V29: =IF(ISNUMBER(S29), "Keep", "Remove") -> Keep | W29: =MID(B29, 5, 11) -> Jan 27 2014 | X29: =VALUE(RIGHT(W29,4)) -> 2014 | Y29: =H29&X29 -> Brazil2014 | Z29: Brazil2014 | AA29: =IFERROR(VLOOKUP(Z29, RISKSHEET!$A$2:$G$1000, 4, FALSE), "Missing") -> -0.05296576 | AB29: =IFERROR(VLOOKUP(Z29, RISKSHEET!$A$2:$G$1000, 5, FALSE), "Missing") -> -0.070290133 | AC29: =IFERROR(VLOOKUP(Z29, RISKSHEET!$A$2:$G$1000, 6, FALSE), "Missing") -> -0.11903097 | AD29: =_xlfn.XLOOKUP(Z29, CREDITRATING!I:I, CREDITRATING!E:E, "Missing") -> BBB | AE29: =_xlfn.XLOOKUP(Z29, CREDITRATING!I:I, CREDITRATING!F:F, "Missing") -> 9
A30: 2605117040 | B30: Mon Jan 27 2014 00:00:00 GMT+0000 (Greenwich Mean Time) | C30: Mon Jan 27 2014 00:00:00 GMT+0000 (Greenwich Mean Time) | D30: 440.81967 | E30: Cia Providencia Industria e Comercio | F30: Consumer Staples | G30: Textiles & Apparel | H30: Brazil | I30: PGI Polimeros do Brasil SA | J30: Consumer Staples | K30: Textiles & Apparel | L30: Brazil | M30: Lazard | N30: Barclays|Citi|Patria Investimentos | O30: Completed | P30: Brazil | Q30: Disclosed Dollar Value Deal | R30: BMFBOVESPA | S30: 35.13 | T30: 29.11 | U30: 21.09 | V30: =IF(ISNUMBER(S30), "Keep", "Remove") -> Keep | W30: =MID(B30, 5, 11) -> Jan 27 2014 | X30: =VALUE(RIGHT(W30,4)) -> 2014 | Y30: =H30&X30 -> Brazil2014 | Z30: Brazil2014 | AA30: =IFERROR(VLOOKUP(Z30, RISKSHEET!$A$2:$G$1000, 4, FALSE), "Missing") -> -0.05296576 | AB30: =IFERROR(VLOOKUP(Z30, RISKSHEET!$A$2:$G$1000, 5, FALSE), "Missing") -> -0.070290133 | AC30: =IFERROR(VLOOKUP(Z30, RISKSHEET!$A$2:$G$1000, 6, FALSE), "Missing") -> -0.11903097 | AD30: =_xlfn.XLOOKUP(Z30, CREDITRATING!I:I, CREDITRATING!E:E, "Missing") -> BBB | AE30: =_xlfn.XLOOKUP(Z30, CREDITRATING!I:I, CREDITRATING!F:F, "Missing") -> 9
A31: 2692849040 | B31: Tue Jan 28 2014 00:00:00 GMT+0000 (Greenwich Mean Time) | C31: Tue Jul 15 2014 00:00:00 GMT+0100 (British Summer Time) | D31: 235.19871 | E31: Rander International Ltd | F31: Energy and Power | G31: Power | H31: China (Mainland) | I31: Surplus Basic Ltd | J31: Financials | K31: Other Financials | L31: Hong Kong | N31: Optima Capital Ltd | O31: Completed | P31: China (Mainland) | Q31: Disclosed Dollar Value Deal | V31: =IF(ISNUMBER(S31), "Keep", "Remove") -> Remove
A32: 2605864040 | B32: Tue Jan 28 2014 00:00:00 GMT+0000 (Greenwich Mean Time) | C32: Tue Jan 28 2014 00:00:00 GMT+0000 (Greenwich Mean Time) | D32: 69.574588 | E32: Shenzhen Hazens Automotive Electronics Co Ltd | F32: High Technology | G32: Software | H32: China (Mainland) | I32: Guangdong Shenglu Telecommunication Tech Co Ltd | J32: Telecommunications | K32: Telecommunications Equipment | L32: China (Mainland) | N32: China Securities Co Ltd | O32: Completed | P32: China (Mainland) | Q32: Disclosed Dollar Value Deal | V32: =IF(ISNUMBER(S32), "Keep", "Remove") -> Remove
A33: 2605024040 | B33: Tue Jan 28 2014 00:00:00 GMT+0000 (Greenwich Mean Time) | C33: Tue Jan 28 2014 00:00:00 GMT+0000 (Greenwich Mean Time) | D33: 816.98889 | E33: Shenzhen Bio-Agriculture Co Ltd | F33: Real Estate | G33: Other Real Estate | H33: China (Mainland) | I33: Shenzhen Investment Ltd | J33: Real Estate | K33: Other Real Estate | L33: Hong Kong | N33: Somerley Ltd | O33: Completed | P33: China (Mainland) | Q33: Disclosed Dollar Value Deal | V33: =IF(ISNUMBER(S33), "Keep", "Remove") -> Remove
A34: 2604971040 | B34: Tue Jan 28 2014 00:00:00 GMT+0000 (Greenwich Mean Time) | C34: Tue Jan 28 2014 00:00:00 GMT+0000 (Greenwich Mean Time) | D34: 102.89261 | E34: ADTECH(Shenzhen)Technology Co Ltd | F34: High Technology | G34: Electronics | H34: China (Mainland) | I34: Shanghai STEP Electric Corp | J34: High Technology | K34: Electronics | L34: China (Mainland) | N34: GF Securities | O34: Completed | P34: China (Mainland) | Q34: Disclosed Dollar Value Deal | V34: =IF(ISNUMBER(S34), "Keep", "Remove") -> Remove
A35: 2604872040 | B35: Tue Jan 28 2014 00:00:00 GMT+0000 (Greenwich Mean Time) | C35: Tue Jan 28 2014 00:00:00 GMT+0000 (Greenwich Mean Time) | D35: 80.922223 | E35: Ningbo Dongxucheng New Materials Technology Co Ltd | F35: Materials | G35: Chemicals | H35: China (Mainland) | I35: Zhejiang Nanyang Technology Co Ltd | J35: High Technology | K35: Semiconductors | L35: China (Mainland) | N35: Qilu Securities Co Ltd | O35: Completed | P35: China (Mainland) | Q35: Disclosed Dollar Value Deal | V35: =IF(ISNUMBER(S35), "Keep", "Remove") -> Remove
A36: 2620181040 | B36: Wed Jan 29 2014 00:00:00 GMT+0000 (Greenwich Mean Time) | C36: Wed Jan 29 2014 00:00:00 GMT+0000 (Greenwich Mean Time) | D36: 90.001197 | E36: OOO Cosstone | F36: Materials | G36: Metals & Mining | H36: Russia | I36: Best Chance Technology Ltd | J36: High Technology | K36: Software | L36: Hong Kong | O36: Completed | P36: Russia | Q36: Disclosed Dollar Value Deal | V36: =IF(ISNUMBER(S36), "Keep", "Remove") -> Remove
A37: 2606402040 | B37: Thu Jan 30 2014 00:00:00 GMT+0000 (Greenwich Mean Time) | C37: Thu Jan 30 2014 00:00:00 GMT+0000 (Greenwich Mean Time) | D37: 259.99439 | E37: Aditya Birla Minacs Worldwide Ltd | F37: Consumer Products and Services | G37: Professional Services | H37: India | I37: Investor Group | J37: Financials | K37: Other Financials | L37: India | N37: Macquarie Capital Group Ltd | O37: Completed | P37: India | Q37: Disclosed Dollar Value Deal | V37: =IF(ISNUMBER(S37), "Keep", "Remove") -> Remove
A38: 2606216040 | B38: Thu Jan 30 2014 00:00:00 GMT+0000 (Greenwich Mean Time) | C38: Fri Mar 28 2014 00:00:00 GMT+0000 (Greenwich Mean Time) | D38: 73.28409 | E38: Montana Industria de Maquinas SA | F38: Industrials | G38: Machinery | H38: Brazil | I38: Kuhn SA | J38: Industrials | K38: Machinery | L38: France | M38: Credit Suisse Group | O38: Completed | P38: Brazil | Q38: Disclosed Dollar Value Deal | V38: =IF(ISNUMBER(S38), "Keep", "Remove") -> Remove
A39: 2607891040 | B39: Fri Jan 31 2014 00:00:00 GMT+0000 (Greenwich Mean Time) | C39: Fri Jan 31 2014 00:00:00 GMT+0000 (Greenwich Mean Time) | D39: 580.85809 | E39: Nanjing Aohe Real Estate Development Co Ltd | F39: Real Estate | G39: Other Real Estate | H39: China (Mainland) | I39: Shanghai Construction Real Estate Co Ltd | J39: Real Estate | K39: Other Real Estate | L39: China (Mainland) | N39: ICBC | O39: Completed | P39: China (Mainland) | Q39: Disclosed Dollar Value Deal | V39: =IF(ISNUMBER(S39), "Keep", "Remove") -> Remove
A40: 2622206040 | B40: Fri Feb 07 2014 00:00:00 GMT+0000 (Greenwich Mean Time) | C40: Fri Feb 07 2014 00:00:00 GMT+0000 (Greenwich Mean Time) | D40: 121.91436 | E40: OAO Bank OTKRYTIYE | F40: Financials | G40: Other Financials | H40: Russia | I40: OAO NOMOS-BANK | J40: Financials | K40: Banks | L40: Russia | O40: Completed | P40: Russia | Q40: Disclosed Dollar Value Deal | V40: =IF(ISNUMBER(S40), "Keep", "Remove") -> Remove
A41: 2609194040 | B41: Fri Feb 07 2014 00:00:00 GMT+0000 (Greenwich Mean Time) | C41: Fri Feb 07 2014 00:00:00 GMT+0000 (Greenwich Mean Time) | D41: 57.821827 | E41: Piramal Glass Ltd | F41: Materials | G41: Containers & Packaging | H41: india | I41: Pel Management Services Pvt Ltd | J41: Financials | K41: Other Financials | L41: India | N41: Kotak Mahindra Capital Company | O41: Completed | P41: India | Q41: Disclosed Dollar Value Deal | R41: National|Bombay | S41: 83.61 | T41: 90.09 | U41: 60.64 | V41: =IF(ISNUMBER(S41), "Keep", "Remove") -> Keep | W41: =MID(B41, 5, 11) -> Feb 07 2014 | X41: =VALUE(RIGHT(W41,4)) -> 2014 | Y41: =H41&X41 -> india2014 | Z41: india2014 | AA41: =IFERROR(VLOOKUP(Z41, RISKSHEET!$A$2:$G$1000, 4, FALSE), "Missing") -> -0.069189385 | AB41: =IFERROR(VLOOKUP(Z41, RISKSHEET!$A$2:$G$1000, 5, FALSE), "Missing") -> -0.99791199 | AC41: =IFERROR(VLOOKUP(Z41, RISKSHEET!$A$2:$G$1000, 6, FALSE), "Missing") -> -0.15735514 | AD41: =_xlfn.XLOOKUP(Z41, CREDITRATING!I:I, CREDITRATING!E:E, "Missing") -> BBB- | AE41: =_xlfn.XLOOKUP(Z41, CREDITRATING!I:I, CREDITRATING!F:F, "Missing") -> 10
A42: 2608047040 | B42: Fri Feb 07 2014 00:00:00 GMT+0000 (Greenwich Mean Time) | C42: Thu May 04 2017 00:00:00 GMT+0100 (British Summer Time) | D42: 251.82531 | E42: Construtora Tenda SA | F42: Real Estate | G42: Real Estate Management & Development | H42: Brazil | I42: Shareholders | J42: Financials | K42: Other Financials | L42: Brazil | M42: Rothschild & Co | O42: Completed | P42: Brazil | Q42: Disclosed Dollar Value Deal | R42: BOVESPA | V42: =IF(ISNUMBER(S42), "Keep", "Remove") -> Remove
A43: 2607860040 | B43: Fri Feb 07 2014 00:00:00 GMT+0000 (Greenwich Mean Time) | C43: Fri Feb 07 2014 00:00:00 GMT+0000 (Greenwich Mean Time) | D43: 316.66413 | E43: Jilin Jinbao Pharmaceutical CO Ltd | F43: Healthcare | G43: Pharmaceuticals | H43: China (Mainland) | I43: Investor Group | J43: Financials | K43: Other Financials | L43: China (Mainland) | N43: Sealand Securities Co Ltd | O43: Completed | P43: China (Mainland) | Q43: Disclosed Dollar Value Deal | V43: =IF(ISNUMBER(S43), "Keep", "Remove") -> Remove
A44: 2608613040 | B44: Mon Feb 10 2014 00:00:00 GMT+0000 (Greenwich Mean Time) | C44: Mon Feb 10 2014 00:00:00 GMT+0000 (Greenwich Mean Time) | D44: 789.80179 | E44: AutoNavi Holdings Ltd | F44: High Technology | G44: IT Consulting & Services | H44: china | I44: Alibaba Group Holding Ltd | J44: Retail | K44: Internet and Catalog Retailing | L44: China (Mainland) | M44: Lazard | N44: Deutsche Bank | O44: Completed | P44: China (Mainland) | Q44: Disclosed Dollar Value Deal | R44: Nasdaq | S44: 26.89 | T44: 38.96 | U44: 33.68 | V44: =IF(ISNUMBER(S44), "Keep", "Remove") -> Keep | W44: =MID(B44, 5, 11) -> Feb 10 2014 | X44: =VALUE(RIGHT(W44,4)) -> 2014 | Y44: =H44&X44 -> china2014 | Z44: china2014 | AA44: =IFERROR(VLOOKUP(Z44, RISKSHEET!$A$2:$G$1000, 4, FALSE), "Missing") -> -0.39605319 | AB44: =IFERROR(VLOOKUP(Z44, RISKSHEET!$A$2:$G$1000, 5, FALSE), "Missing") -> -0.52258402 | AC44: =IFERROR(VLOOKUP(Z44, RISKSHEET!$A$2:$G$1000, 6, FALSE), "Missing") -> -0.0051206895 | AD44: =_xlfn.XLOOKUP(Z44, CREDITRATING!I:I, CREDITRATING!E:E, "Missing") -> A+ | AE44: =_xlfn.XLOOKUP(Z44, CREDITRATING!I:I, CREDITRATING!F:F, "Missing") -> 5
A45: 2609088040 | B45: Wed Feb 12 2014 00:00:00 GMT+0000 (Greenwich Mean Time) | C45: Thu Dec 04 2014 00:00:00 GMT+0000 (Greenwich Mean Time) | D45: 141.31603 | E45: Chongqing Transporation Equipment Financial Leasing Co Ltd | F45: Financials | G45: Credit Institutions | H45: China (Mainland) | I45: Sichuan Western Resources Holding Co Ltd | J45: Materials | K45: Metals & Mining | L45: China (Mainland) | N45: China Minzu Securities Co Ltd | O45: Completed | P45: China (Mainland) | Q45: Disclosed Dollar Value Deal | V45: =IF(ISNUMBER(S45), "Keep", "Remove") -> Remove
A46: 2609085040 | B46: Wed Feb 12 2014 00:00:00 GMT+0000 (Greenwich Mean Time) | C46: Thu Dec 04 2014 00:00:00 GMT+0000 (Greenwich Mean Time) | D46: 53.0292 | E46: Chongqing Hengtong Passenger Bus Co Ltd | F46: Industrials | G46: Transportation & Infrastructure | H46: China (Mainland) | I46: Sichuan Western Resources Holding Co Ltd | J46: Materials | K46: Metals & Mining | L46: China (Mainland) | N46: China Minzu Securities Co Ltd | O46: Completed | P46: China (Mainland) | Q46: Disclosed Dollar Value Deal | V46: =IF(ISNUMBER(S46), "Keep", "Remove") -> Remove
A47: 2610008040 | B47: Fri Feb 14 2014 00:00:00 GMT+0000 (Greenwich Mean Time) | C47: Fri Feb 14 2014 00:00:00 GMT+0000 (Greenwich Mean Time) | D47: 132.49992 | E47: Lefeng.com Ltd | F47: Retail | G47: Internet and Catalog Retailing | H47: China (Mainland) | I47: Vipshop Holdings Ltd | J47: Retail | K47: Internet and Catalog Retailing | L47: China (Mainland) | M47: China Renaissance Holdings Ltd | O47: Completed | P47: China (Mainland) | Q47: Disclosed Dollar Value Deal | V47: =IF(ISNUMBER(S47), "Keep", "Remove") -> Remove
A48: 2610413040 | B48: Mon Feb 17 2014 00:00:00 GMT+0000 (Greenwich Mean Time) | C48: Mon Feb 17 2014 00:00:00 GMT+0000 (Greenwich Mean Time) | D48: 135.2265 | E48: Point Jingan | F48: Real Estate | G48: Non Residential | H48: China (Mainland) | I48: Mary Kay Inc | J48: Consumer Products and Services | K48: Other Consumer Products | L48: United States | O48: Completed | P48: China (Mainland) | Q48: Disclosed Dollar Value Deal | V48: =IF(ISNUMBER(S48), "Keep", "Remove") -> Remove
A49: 2581449040 | B49: Mon Feb 17 2014 00:00:00 GMT+0000 (Greenwich Mean Time) | C49: Mon Feb 17 2014 00:00:00 GMT+0000 (Greenwich Mean Time) | D49: 328.27961 | E49: WF2 Holding SA | F49: Financials | G49: Other Financials | H49: Brazil | I49: CPFL Energias Renovaveis SA | J49: Energy and Power | K49: Power | L49: Brazil | M49: Bank of America Merrill Lynch | N49: Itau Unibanco|Banco BTG Pactual SA | O49: Completed | P49: Brazil | Q49: Disclosed Dollar Value Deal | V49: =IF(ISNUMBER(S49), "Keep", "Remove") -> Remove
A50: 2610321040 | B50: Tue Feb 18 2014 00:00:00 GMT+0000 (Greenwich Mean Time) | C50: Tue Feb 18 2014 00:00:00 GMT+0000 (Greenwich Mean Time) | D50: 79.319939 | E50: Shenzhen Jiaai Motor Co Ltd | F50: Industrials | G50: Machinery | H50: China (Mainland) | I50: Jinlong Machinery&Electronic Co Ltd | J50: Energy and Power | K50: Other Energy & Power | L50: China (Mainland) | N50: Guosen Securities Co Ltd | O50: Completed | P50: China (Mainland) | Q50: Disclosed Dollar Value Deal | V50: =IF(ISNUMBER(S50), "Keep", "Remove") -> Remove
A51: 2610299040 | B51: Tue Feb 18 2014 00:00:00 GMT+0000 (Greenwich Mean Time) | C51: Tue Feb 18 2014 00:00:00 GMT+0000 (Greenwich Mean Time) | D51: 83.424371 | E51: Wuxi Boyi Photoelectric Technology Co Ltd | F51: High Technology | G51: Semiconductors | H51: China (Mainland) | I51: Jinlong Machinery&Electronic Co Ltd | J51: Energy and Power | K51: Other Energy & Power | L51: China (Mainland) | N51: Guosen Securities Co Ltd | O51: Completed | P51: China (Mainland) | Q51: Disclosed Dollar Value Deal | V51: =IF(ISNUMBER(S51), "Keep", "Remove") -> Remove
A52: 2580881040 | B52: Tue Feb 18 2014 00:00:00 GMT+0000 (Greenwich Mean Time) | C52: Tue Feb 18 2014 00:00:00 GMT+0000 (Greenwich Mean Time) | D52: 1046.0025 | E52: Kerr-McGee China Petroleum Ltd | F52: Energy and Power | G52: Oil & Gas | H52: China (Mainland) | I52: Win Business Energy(Caofeidian)Ltd | J52: Financials | K52: Other Financials | L52: Hong Kong | M52: Jefferies LLC | N52: BOCI Asia | O52: Completed | P52: China (Mainland) | Q52: Disclosed Dollar Value Deal | V52: =IF(ISNUMBER(S52), "Keep", "Remove") -> Remove
A53: 2580357040 | B53: Tue Feb 18 2014 00:00:00 GMT+0000 (Greenwich Mean Time) | C53: Tue Feb 18 2014 00:00:00 GMT+0000 (Greenwich Mean Time) | D53: 265.55324 | E53: WTorre SPE XIV Investimentos Imobiliarios Ltda | F53: Real Estate | G53: Non Residential | H53: Brazil | I53: Investor Group | J53: Financials | K53: Other Financials | L53: Brazil | M53: Itau Unibanco | O53: Completed | P53: Brazil | Q53: Disclosed Dollar Value Deal | V53: =IF(ISNUMBER(S53), "Keep", "Remove") -> Remove
A54: 2610818040 | B54: Wed Feb 19 2014 00:00:00 GMT+0000 (Greenwich Mean Time) | C54: Wed Feb 19 2014 00:00:00 GMT+0000 (Greenwich Mean Time) | D54: 71.837662 | E54: Changshu Changjiang International Port Co Ltd | F54: Industrials | G54: Transportation & Infrastructure | H54: China (Mainland) | I54: Changshu Xinghua Port Co Ltd | J54: Industrials | K54: Transportation & Infrastructure | L54: China (Mainland) | O54: Completed | P54: China (Mainland) | Q54: Disclosed Dollar Value Deal | V54: =IF(ISNUMBER(S54), "Keep", "Remove") -> Remove
A55: 2614176040 | B55: Thu Feb 20 2014 00:00:00 GMT+0000 (Greenwich Mean Time) | C55: Thu Feb 20 2014 00:00:00 GMT+0000 (Greenwich Mean Time) | D55: 112.19043 | E55: OAO Taganrogskiy aviatsionnyi nauchno-tekhnichekiy kompleks im G M Beriyeva | F55: Industrials | G55: Aerospace & Defense | H55: Russia | I55: United Aircraft Corp PJSC | J55: Industrials | K55: Aerospace & Defense | L55: Russia | O55: Completed | P55: Russia | Q55: Disclosed Dollar Value Deal | R55: Russian TS | V55: =IF(ISNUMBER(S55), "Keep", "Remove") -> Remove
A56: 2612021040 | B56: Thu Feb 20 2014 00:00:00 GMT+0000 (Greenwich Mean Time) | C56: Thu Feb 20 2014 00:00:00 GMT+0000 (Greenwich Mean Time) | D56: 76.982509 | E56: Wangze(Dalian)Enterprise Co Ltd | F56: Real Estate | G56: Other Real Estate | H56: China (Mainland) | I56: Somerset Grand Central Dalian Holdings Pte Ltd | J56: Financials | K56: Other Financials | L56: Singapore | O56: Completed | P56: China (Mainland) | Q56: Disclosed Dollar Value Deal | V56: =IF(ISNUMBER(S56), "Keep", "Remove") -> Remove
A57: 2611141040 | B57: Thu Feb 20 2014 00:00:00 GMT+0000 (Greenwich Mean Time) | C57: Tue May 13 2014 00:00:00 GMT+0100 (British Summer Time) | D57: 167.38176 | E57: Huizhou Zhongzhou Property Co Ltd | F57: Real Estate | G57: Other Real Estate | H57: China (Mainland) | I57: Shenzhen Changcheng Investment Holding Co Ltd | J57: Real Estate | K57: Residential | L57: China (Mainland) | O57: Completed | P57: China (Mainland) | Q57: Disclosed Dollar Value Deal | V57: =IF(ISNUMBER(S57), "Keep", "Remove") -> Remove
A58: 2611126040 | B58: Thu Feb 20 2014 00:00:00 GMT+0000 (Greenwich Mean Time) | C58: Thu Feb 20 2014 00:00:00 GMT+0000 (Greenwich Mean Time) | D58: 169.90515 | E58: Hefei Tongzhi Electrical Machinery Control Technology Co Ltd | F58: Industrials | G58: Machinery | H58: China (Mainland) | I58: Jiangsu Yinhe Electronics Co Ltd | J58: Telecommunications | K58: Telecommunications Equipment | L58: China (Mainland) | N58: Donghai Securities Co Ltd | O58: Completed | P58: China (Mainland) | Q58: Disclosed Dollar Value Deal | V58: =IF(ISNUMBER(S58), "Keep", "Remove") -> Remove
A59: 2508227040 | B59: Thu Feb 20 2014 00:00:00 GMT+0000 (Greenwich Mean Time) | C59: Thu Feb 20 2014 00:00:00 GMT+0000 (Greenwich Mean Time) | D59: 118.02998 | E59: Hainan Minsheng Changliu Oil& Gas Storage&Transportation Co Ltd | F59: Energy and Power | G59: Oil & Gas | H59: China (Mainland) | I59: Beijing Capital Development Co Ltd | J59: Real Estate | K59: Other Real Estate | L59: China (Mainland) | O59: Completed | P59: China (Mainland) | Q59: Disclosed Dollar Value Deal | V59: =IF(ISNUMBER(S59), "Keep", "Remove") -> Remove
A60: 2611843040 | B60: Fri Feb 21 2014 00:00:00 GMT+0000 (Greenwich Mean Time) | C60: Fri Feb 21 2014 00:00:00 GMT+0000 (Greenwich Mean Time) | D60: 87.383119 | E60: ICRA Ltd | F60: Consumer Products and Services | G60: Professional Services | H60: india | I60: Moody's Singapore Pte Ltd | J60: Consumer Products and Services | K60: Professional Services | L60: Singapore | N60: Citi|Price Waterhouse | O60: Completed | P60: India | Q60: Disclosed Dollar Value Deal | R60: Bombay|National | S60: 58.29 | T60: 54.59 | U60: 54.15 | V60: =IF(ISNUMBER(S60), "Keep", "Remove") -> Keep | W60: =MID(B60, 5, 11) -> Feb 21 2014 | X60: =VALUE(RIGHT(W60,4)) -> 2014 | Y60: =H60&X60 -> india2014 | Z60: india2014 | AA60: =IFERROR(VLOOKUP(Z60, RISKSHEET!$A$2:$G$1000, 4, FALSE), "Missing") -> -0.069189385 | AB60: =IFERROR(VLOOKUP(Z60, RISKSHEET!$A$2:$G$1000, 5, FALSE), "Missing") -> -0.99791199 | AC60: =IFERROR(VLOOKUP(Z60, RISKSHEET!$A$2:$G$1000, 6, FALSE), "Missing") -> -0.15735514 | AD60: =_xlfn.XLOOKUP(Z60, CREDITRATING!I:I, CREDITRATING!E:E, "Missing") -> BBB- | AE60: =_xlfn.XLOOKUP(Z60, CREDITRATING!I:I, CREDITRATING!F:F, "Missing") -> 10
A61: 2611659040 | B61: Fri Feb 21 2014 00:00:00 GMT+0000 (Greenwich Mean Time) | C61: Sat Apr 12 2014 00:00:00 GMT+0100 (British Summer Time) | D61: 335.34563 | E61: Chenzhou Fengyue Environmental Technology Co Ltd | F61: Energy and Power | G61: Water and Waste Management | H61: China (Mainland) | I61: Shanghai Dingli Technology Development(Group)Co Ltd | J61: Real Estate | K61: Other Real Estate | L61: China (Mainland) | N61: Southwest Securities Co Ltd | O61: Completed | P61: China (Mainland) | Q61: Disclosed Dollar Value Deal | V61: =IF(ISNUMBER(S61), "Keep", "Remove") -> Remove
A62: 2595434040 | B62: Sat Feb 22 2014 00:00:00 GMT+0000 (Greenwich Mean Time) | C62: Sat Feb 22 2014 00:00:00 GMT+0000 (Greenwich Mean Time) | D62: 650.1182 | E62: Xinhua Hydropower Co Ltd | F62: Energy and Power | G62: Power | H62: China (Mainland) | I62: China Nuclear Engineering & Construction Corp Ltd | J62: Energy and Power | K62: Power | L62: China (Mainland) | O62: Completed | P62: China (Mainland) | Q62: Disclosed Dollar Value Deal | V62: =IF(ISNUMBER(S62), "Keep", "Remove") -> Remove
A63: 2612190040 | B63: Mon Feb 24 2014 00:00:00 GMT+0000 (Greenwich Mean Time) | C63: Mon Oct 06 2014 00:00:00 GMT+0100 (British Summer Time) | D63: 778.20138 | E63: Cosan SA Industria e Comercio-Logistic Assets | F63: Industrials | G63: Transportation & Infrastructure | H63: Brazil | I63: Shareholders | J63: Financials | K63: Other Financials | L63: Brazil | M63: Rothschild & Co|Credit Suisse Group|Bank of America Merrill Lynch|Itau Unibanco|Banco BTG Pactual SA | O63: Completed | P63: Brazil | Q63: Disclosed Dollar Value Deal | V63: =IF(ISNUMBER(S63), "Keep", "Remove") -> Remove
A64: 2611976040 | B64: Mon Feb 24 2014 00:00:00 GMT+0000 (Greenwich Mean Time) | C64: Mon Feb 24 2014 00:00:00 GMT+0000 (Greenwich Mean Time) | D64: 163.98281 | E64: Chongqing BOE Optoelectronics Co Ltd | F64: High Technology | G64: Semiconductors | H64: China (Mainland) | I64: Chongqing Jiangbeizui CBD Investment Group Co Ltd | J64: Financials | K64: Other Financials | L64: China (Mainland) | O64: Completed | P64: China (Mainland) | Q64: Disclosed Dollar Value Deal | V64: =IF(ISNUMBER(S64), "Keep", "Remove") -> Remove
A65: 2611942040 | B65: Mon Feb 24 2014 00:00:00 GMT+0000 (Greenwich Mean Time) | C65: Mon Feb 24 2014 00:00:00 GMT+0000 (Greenwich Mean Time) | D65: 139.13007 | E65: Shanghai Zhicheng Biological Technology Co Ltd | F65: Healthcare | G65: Biotechnology | H65: China (Mainland) | I65: Zhongyuan Union Stem Cell Bioengineering Co Ltd | J65: Healthcare | K65: Biotechnology | L65: China (Mainland) | N65: Hua Ying Securities Co Ltd | O65: Completed | P65: China (Mainland) | Q65: Disclosed Dollar Value Deal | V65: =IF(ISNUMBER(S65), "Keep", "Remove") -> Remove
A66: 2534755040 | B66: Mon Feb 24 2014 00:00:00 GMT+0000 (Greenwich Mean Time) | C66: Mon Feb 24 2014 00:00:00 GMT+0000 (Greenwich Mean Time) | D66: 60 | E66: Brady Corp-Die-Cut Business | F66: Materials | G66: Paper & Forest Products | H66: China (Mainland) | I66: Boyd Corp | J66: Industrials | K66: Other Industrials | L66: United States | M66: PricewaterhouseCoopers | O66: Completed | P66: China (Mainland) | Q66: Disclosed Dollar Value Deal | V66: =IF(ISNUMBER(S66), "Keep", "Remove") -> Remove
A67: 2612405040 | B67: Tue Feb 25 2014 00:00:00 GMT+0000 (Greenwich Mean Time) | C67: Tue Feb 25 2014 00:00:00 GMT+0000 (Greenwich Mean Time) | D67: 128.26636 | E67: Shanghai Zhezhong(Group)Co Ltd | F67: Financials | G67: Other Financials | H67: China (Mainland) | I67: Shanghai Zhezhong Construction Co Ltd | J67: Materials | K67: Metals & Mining | L67: China (Mainland) | N67: Minsheng Securities Co Ltd | O67: Completed | P67: China (Mainland) | Q67: Disclosed Dollar Value Deal | V67: =IF(ISNUMBER(S67), "Keep", "Remove") -> Remove
A68: 2612346040 | B68: Tue Feb 25 2014 00:00:00 GMT+0000 (Greenwich Mean Time) | C68: Tue Feb 25 2014 00:00:00 GMT+0000 (Greenwich Mean Time) | D68: 57.279363 | E68: Langfang Shengbin Real Estate Development Co Ltd | F68: Real Estate | G68: Other Real Estate | H68: China (Mainland) | I68: Langfang Jingyu Real Estate Development Co Ltd | J68: Real Estate | K68: Other Real Estate | L68: China (Mainland) | O68: Completed | P68: China (Mainland) | Q68: Disclosed Dollar Value Deal | V68: =IF(ISNUMBER(S68), "Keep", "Remove") -> Remove
A69: 2613558040 | B69: Wed Feb 26 2014 00:00:00 GMT+0000 (Greenwich Mean Time) | C69: Wed Feb 26 2014 00:00:00 GMT+0000 (Greenwich Mean Time) | D69: 65.313587 | E69: Yichang Changjiang Aluminum Co Ltd | F69: Materials | G69: Metals & Mining | H69: China (Mainland) | I69: Investor Group | J69: Financials | K69: Other Financials | L69: China (Mainland) | O69: Completed | P69: China (Mainland) | Q69: Disclosed Dollar Value Deal | V69: =IF(ISNUMBER(S69), "Keep", "Remove") -> Remove
A70: 2613833040 | B70: Thu Feb 27 2014 00:00:00 GMT+0000 (Greenwich Mean Time) | C70: Thu Feb 27 2014 00:00:00 GMT+0000 (Greenwich Mean Time) | D70: 80.759788 | E70: Degas Empreendimentos e Participacoes SA | F70: Real Estate | G70: Non Residential | H70: Brazil | I70: CTBH Fundo de Investimentos Imobiliarios FII | J70: Real Estate | K70: REITs | L70: Brazil | M70: Banco BTG Pactual SA | N70: Itau Unibanco | O70: Completed | P70: Brazil | Q70: Disclosed Dollar Value Deal | V70: =IF(ISNUMBER(S70), "Keep", "Remove") -> Remove
A71: 2613495040 | B71: Thu Feb 27 2014 00:00:00 GMT+0000 (Greenwich Mean Time) | C71: Mon Jun 30 2014 00:00:00 GMT+0100 (British Summer Time) | D71: 580.30821 | E71: Dihon Pharmaceutical Group Co Ltd | F71: Healthcare | G71: Pharmaceuticals | H71: China (Mainland) | I71: Bayer AG | J71: Healthcare | K71: Pharmaceuticals | L71: Germany | M71: KPMG | N71: Morgan Stanley | O71: Completed | P71: China (Mainland) | Q71: Disclosed Dollar Value Deal | V71: =IF(ISNUMBER(S71), "Keep", "Remove") -> Remove
A72: 3073001040 | B72: Fri Feb 28 2014 00:00:00 GMT+0000 (Greenwich Mean Time) | C72: Wed Feb 01 2017 00:00:00 GMT+0000 (Greenwich Mean Time) | D72: 76.252579 | E72: REC Sao Bernardo Securitizadora De Creditos Imobiliarios SA | F72: Real Estate | G72: REITs | H72: Brazil | I72: LPP III Empreendimentos & Participacoes SA | J72: Industrials | K72: Other Industrials | L72: Brazil | O72: Completed | P72: Brazil | Q72: Disclosed Dollar Value Deal | V72: =IF(ISNUMBER(S72), "Keep", "Remove") -> Remove
A73: 2615613040 | B73: Fri Feb 28 2014 00:00:00 GMT+0000 (Greenwich Mean Time) | C73: Fri Feb 28 2014 00:00:00 GMT+0000 (Greenwich Mean Time) | D73: 1177.4226 | E73: BR Properties SA-Portfolio of Logistic Assets | F73: Industrials | G73: Other Industrials | H73: Brazil | I73: LPP Empreendimentos e Participacoes Ltda | J73: Industrials | K73: Other Industrials | L73: Brazil | M73: Banco BTG Pactual SA | N73: Citi | O73: Completed | P73: Brazil | Q73: Disclosed Dollar Value Deal | V73: =IF(ISNUMBER(S73), "Keep", "Remove") -> Remove
A74: 2613753040 | B74: Fri Feb 28 2014 00:00:00 GMT+0000 (Greenwich Mean Time) | C74: Fri Feb 28 2014 00:00:00 GMT+0000 (Greenwich Mean Time) | D74: 354.2833 | E74: Shanghai Jingsheng Real Estate Development Co Ltd | F74: Real Estate | G74: Other Real Estate | H74: China (Mainland) | I74: Financial Street Holdings Co Ltd | J74: Real Estate | K74: Other Real Estate | L74: China (Mainland) | M74: Goldman Sachs & Co | O74: Completed | P74: China (Mainland) | Q74: Disclosed Dollar Value Deal | V74: =IF(ISNUMBER(S74), "Keep", "Remove") -> Remove
A75: 2614017040 | B75: Sat Mar 01 2014 00:00:00 GMT+0000 (Greenwich Mean Time) | C75: Sat Mar 01 2014 00:00:00 GMT+0000 (Greenwich Mean Time) | D75: 97.643536 | E75: Xibei Bearing Co Ltd | F75: Industrials | G75: Other Industrials | H75: China (Mainland) | I75: Ningxia Baota Petrochemical Group Co Ltd | J75: Energy and Power | K75: Oil & Gas | L75: China (Mainland) | O75: Completed | P75: China (Mainland) | Q75: Disclosed Dollar Value Deal | R75: Shenzhen | T75: -10.93 | U75: -5.69 | V75: =IF(ISNUMBER(S75), "Keep", "Remove") -> Remove
A76: 2617235040 | B76: Mon Mar 03 2014 00:00:00 GMT+0000 (Greenwich Mean Time) | C76: Mon Mar 03 2014 00:00:00 GMT+0000 (Greenwich Mean Time) | D76: 77.307842 | E76: Cosmic Summit Ltd | F76: Materials | G76: Chemicals | H76: China (Mainland) | I76: Superb Summit International Energy Holdings Ltd | J76: Materials | K76: Metals & Mining | L76: Hong Kong | N76: CCB International Capital Ltd | O76: Completed | P76: China (Mainland) | Q76: Disclosed Dollar Value Deal | V76: =IF(ISNUMBER(S76), "Keep", "Remove") -> Remove
A77: 2618281040 | B77: Tue Mar 04 2014 00:00:00 GMT+0000 (Greenwich Mean Time) | C77: Tue Mar 04 2014 00:00:00 GMT+0000 (Greenwich Mean Time) | D77: 71.622986 | E77: Hefei Chang'an Automobiles Co Ltd | F77: Industrials | G77: Automobiles & Components | H77: China (Mainland) | I77: Chongqing Changan Automobile Co Ltd | J77: Industrials | K77: Automobiles & Components | L77: China (Mainland) | O77: Completed | P77: China (Mainland) | Q77: Disclosed Dollar Value Deal | V77: =IF(ISNUMBER(S77), "Keep", "Remove") -> Remove
A78: 2614593040 | B78: Tue Mar 04 2014 00:00:00 GMT+0000 (Greenwich Mean Time) | C78: Tue Mar 04 2014 00:00:00 GMT+0000 (Greenwich Mean Time) | D78: 71.463454 | E78: Shenzhen Smoore Technology Ltd | F78: High Technology | G78: Electronics | H78: China (Mainland) | I78: EVE Energy Co Ltd | J78: Energy and Power | K78: Other Energy & Power | L78: China (Mainland) | O78: Completed | P78: China (Mainland) | Q78: Disclosed Dollar Value Deal | V78: =IF(ISNUMBER(S78), "Keep", "Remove") -> Remove
A79: 2614418040 | B79: Tue Mar 04 2014 00:00:00 GMT+0000 (Greenwich Mean Time) | C79: Tue Mar 04 2014 00:00:00 GMT+0000 (Greenwich Mean Time) | D79: 82.153258 | E79: D&M Intelligence Technology Co Ltd | F79: High Technology | G79: Software | H79: China (Mainland) | I79: Shaanxi J & R Fire Protection Co Ltd | J79: Industrials | K79: Machinery | L79: China (Mainland) | N79: Caitong Securities Co Ltd | O79: Completed | P79: China (Mainland) | Q79: Disclosed Dollar Value Deal | V79: =IF(ISNUMBER(S79), "Keep", "Remove") -> Remove
A80: 2618277040 | B80: Wed Mar 05 2014 00:00:00 GMT+0000 (Greenwich Mean Time) | C80: Wed Sep 17 2014 00:00:00 GMT+0100 (British Summer Time) | D80: 185.85008 | E80: China Resources Wandong Medical Equipment Co Ltd | F80: Healthcare | G80: Healthcare Equipment & Supplies | H80: China (Mainland) | I80: Jiangsu Yuyue Technology Development Co Ltd | J80: High Technology | K80: Electronics | L80: China (Mainland) | O80: Completed | P80: China (Mainland) | Q80: Disclosed Dollar Value Deal | R80: Shanghai | U80: -19.72 | V80: =IF(ISNUMBER(S80), "Keep", "Remove") -> Remove
A81: 2615279040 | B81: Wed Mar 05 2014 00:00:00 GMT+0000 (Greenwich Mean Time) | C81: Wed Mar 05 2014 00:00:00 GMT+0000 (Greenwich Mean Time) | D81: 59.107775 | E81: Usina Rio Pardo SA-Cogeneration Plant | F81: Energy and Power | G81: Alternative Energy Sources | H81: Brazil | I81: Albioma SA | J81: Energy and Power | K81: Power | L81: France | M81: Itau Unibanco | N81: Santander Corp & Invest Bkg | O81: Completed | P81: Brazil | Q81: Disclosed Dollar Value Deal | V81: =IF(ISNUMBER(S81), "Keep", "Remove") -> Remove
A82: 2615219040 | B82: Wed Mar 05 2014 00:00:00 GMT+0000 (Greenwich Mean Time) | C82: Wed Mar 05 2014 00:00:00 GMT+0000 (Greenwich Mean Time) | D82: 58.515503 | E82: Beijing Nasoft Co Ltd | F82: High Technology | G82: Software | H82: China (Mainland) | I82: Beijing Lanxum Technology Co Ltd | J82: Consumer Products and Services | K82: Educational Services | L82: China (Mainland) | N82: Huatai United Securities Co | O82: Completed | P82: China (Mainland) | Q82: Disclosed Dollar Value Deal | V82: =IF(ISNUMBER(S82), "Keep", "Remove") -> Remove
A83: 2616756040 | B83: Fri Mar 07 2014 00:00:00 GMT+0000 (Greenwich Mean Time) | C83: Fri Mar 07 2014 00:00:00 GMT+0000 (Greenwich Mean Time) | D83: 117.96341 | E83: Annuity Properties Ltd | F83: Real Estate | G83: REITs | H83: South Africa | I83: Redefine Properties Ltd | J83: Real Estate | K83: REITs | L83: South Africa | N83: Java Capital (Proprietary) Ltd | O83: Completed | P83: South Africa | Q83: Disclosed Dollar Value Deal | R83: Johannesbu | V83: =IF(ISNUMBER(S83), "Keep", "Remove") -> Remove
A84: 2616595040 | B84: Sat Mar 08 2014 00:00:00 GMT+0000 (Greenwich Mean Time) | C84: Sat Mar 08 2014 00:00:00 GMT+0000 (Greenwich Mean Time) | D84: 80.351011 | E84: Hangzhou Energy & Environmental Engineering Co Ltd | F84: Energy and Power | G84: Power | H84: China (Mainland) | I84: Jiang Su Wei Er Li Huan Bao Ke Ji Gu Fen You Xian Gong Si | J84: Energy and Power | K84: Water and Waste Management | L84: China (Mainland) | N84: Guosen Securities Co Ltd | O84: Completed | P84: China (Mainland) | Q84: Disclosed Dollar Value Deal | V84: =IF(ISNUMBER(S84), "Keep", "Remove") -> Remove
A85: 2623953040 | B85: Sun Mar 09 2014 00:00:00 GMT+0000 (Greenwich Mean Time) | C85: Wed Mar 19 2014 00:00:00 GMT+0000 (Greenwich Mean Time) | D85: 129.16976 | E85: Shanghai Icson E-Commerce Development Co Ltd | F85: High Technology | G85: Internet Software & Services | H85: China (Mainland) | I85: JD.com Inc | J85: Consumer Products and Services | K85: Professional Services | L85: China (Mainland) | M85: Barclays PLC | N85: Bank of America Merrill Lynch|China Renaissance Holdings Ltd | O85: Completed | P85: China (Mainland) | Q85: Disclosed Dollar Value Deal | V85: =IF(ISNUMBER(S85), "Keep", "Remove") -> Remove
A86: 2617121040 | B86: Sun Mar 09 2014 00:00:00 GMT+0000 (Greenwich Mean Time) | C86: Mon Mar 10 2014 00:00:00 GMT+0000 (Greenwich Mean Time) | D86: 1923.9948 | E86: Tencent Holdings Ltd-Businesses | F86: High Technology | G86: Internet Software & Services | H86: China (Mainland) | I86: JD.com Inc | J86: Consumer Products and Services | K86: Professional Services | L86: China (Mainland) | M86: Barclays | N86: Bank of America Merrill Lynch|China Renaissance Holdings Ltd | O86: Completed | P86: China (Mainland) | Q86: Disclosed Dollar Value Deal | V86: =IF(ISNUMBER(S86), "Keep", "Remove") -> Remove
A87: 2625276040 | B87: Mon Mar 10 2014 00:00:00 GMT+0000 (Greenwich Mean Time) | C87: Mon Mar 10 2014 00:00:00 GMT+0000 (Greenwich Mean Time) | D87: 190.2851 | E87: Nanjing Gangning Real Estate Co Ltd | F87: Real Estate | G87: Other Real Estate | H87: China (Mainland) | I87: Southeast Asia Shenfu Co Ltd | J87: Financials | K87: Asset Management | L87: Hong Kong | O87: Completed | P87: China (Mainland) | Q87: Disclosed Dollar Value Deal | V87: =IF(ISNUMBER(S87), "Keep", "Remove") -> Remove
A88: 2625274040 | B88: Mon Mar 10 2014 00:00:00 GMT+0000 (Greenwich Mean Time) | C88: Mon Mar 10 2014 00:00:00 GMT+0000 (Greenwich Mean Time) | D88: 146.62235 | E88: Nanjing Longjiangwan Real Estate Co Ltd | F88: Real Estate | G88: Other Real Estate | H88: China (Mainland) | I88: Southeast Asia Shenfu Co Ltd | J88: Financials | K88: Asset Management | L88: Hong Kong | O88: Completed | P88: China (Mainland) | Q88: Disclosed Dollar Value Deal | V88: =IF(ISNUMBER(S88), "Keep", "Remove") -> Remove
A89: 2620130040 | B89: Mon Mar 10 2014 00:00:00 GMT+0000 (Greenwich Mean Time) | C89: Mon Mar 10 2014 00:00:00 GMT+0000 (Greenwich Mean Time) | D89: 79.826662 | E89: Suzhou Industrial Park Jian Wu Heng Ye Property Development Co Ltd | F89: Real Estate | G89: Other Real Estate | H89: China (Mainland) | I89: SIP Genway Group Co Ltd | J89: Real Estate | K89: Other Real Estate | L89: China (Mainland) | O89: Completed | P89: China (Mainland) | Q89: Disclosed Dollar Value Deal | V89: =IF(ISNUMBER(S89), "Keep", "Remove") -> Remove
A90: 2616987040 | B90: Mon Mar 10 2014 00:00:00 GMT+0000 (Greenwich Mean Time) | C90: Mon Mar 10 2014 00:00:00 GMT+0000 (Greenwich Mean Time) | D90: 343.6001 | E90: Sonae Sierra Brazil BV Sarl | F90: Real Estate | G90: Other Real Estate | H90: Brazil | I90: Alexander Otto | J90: Financials | K90: Other Financials | L90: Germany | O90: Completed | P90: Brazil | Q90: Disclosed Dollar Value Deal | V90: =IF(ISNUMBER(S90), "Keep", "Remove") -> Remove
A91: 2616977040 | B91: Mon Mar 10 2014 00:00:00 GMT+0000 (Greenwich Mean Time) | C91: Mon Mar 10 2014 00:00:00 GMT+0000 (Greenwich Mean Time) | D91: 516.42244 | E91: Montage Technology Group Ltd | F91: High Technology | G91: Semiconductors | H91: china | I91: Investor Group | J91: Financials | K91: Other Financials | L91: China (Mainland) | M91: Stifel Nicolaus & Co Inc | N91: China International Capital Co|CITIC Securities Co Ltd|Barclays PLC | O91: Completed | P91: China (Mainland) | Q91: Disclosed Dollar Value Deal | R91: Nasdaq | S91: 33.81 | T91: 46.99 | U91: 46.01 | V91: =IF(ISNUMBER(S91), "Keep", "Remove") -> Keep | W91: =MID(B91, 5, 11) -> Mar 10 2014 | X91: =VALUE(RIGHT(W91,4)) -> 2014 | Y91: =H91&X91 -> china2014 | Z91: china2014 | AA91: =IFERROR(VLOOKUP(Z91, RISKSHEET!$A$2:$G$1000, 4, FALSE), "Missing") -> -0.39605319 | AB91: =IFERROR(VLOOKUP(Z91, RISKSHEET!$A$2:$G$1000, 5, FALSE), "Missing") -> -0.52258402 | AC91: =IFERROR(VLOOKUP(Z91, RISKSHEET!$A$2:$G$1000, 6, FALSE), "Missing") -> -0.0051206895 | AD91: =_xlfn.XLOOKUP(Z91, CREDITRATING!I:I, CREDITRATING!E:E, "Missing") -> A+ | AE91: =_xlfn.XLOOKUP(Z91, CREDITRATING!I:I, CREDITRATING!F:F, "Missing") -> 5
A92: 2616560040 | B92: Mon Mar 10 2014 00:00:00 GMT+0000 (Greenwich Mean Time) | C92: Mon Mar 10 2014 00:00:00 GMT+0000 (Greenwich Mean Time) | D92: 68.163661 | E92: Shanghai Yuanfang Groundwork Engineering Co Ltd | F92: Industrials | G92: Building/Construction & Engineering | H92: China (Mainland) | I92: China Zhonghua Geotechnical Engineering Co Ltd | J92: Industrials | K92: Building/Construction & Engineering | L92: China (Mainland) | N92: Haitong Securities Co Ltd | O92: Completed | P92: China (Mainland) | Q92: Disclosed Dollar Value Deal | V92: =IF(ISNUMBER(S92), "Keep", "Remove") -> Remove
A93: 2616542040 | B93: Mon Mar 10 2014 00:00:00 GMT+0000 (Greenwich Mean Time) | C93: Mon Mar 10 2014 00:00:00 GMT+0000 (Greenwich Mean Time) | D93: 69.919685 | E93: Shanghai Qiangjin Foundation Engineering Co Ltd | F93: Industrials | G93: Building/Construction & Engineering | H93: China (Mainland) | I93: China Zhonghua Geotechnical Engineering Co Ltd | J93: Industrials | K93: Building/Construction & Engineering | L93: China (Mainland) | N93: Haitong Securities Co Ltd | O93: Completed | P93: China (Mainland) | Q93: Disclosed Dollar Value Deal | V93: =IF(ISNUMBER(S93), "Keep", "Remove") -> Remove
A94: 2632015040 | B94: Tue Mar 11 2014 00:00:00 GMT+0000 (Greenwich Mean Time) | C94: Fri Jun 06 2014 00:00:00 GMT+0100 (British Summer Time) | D94: 571.37828 | E94: Shanghai Securities Co Ltd | F94: Financials | G94: Brokerage | H94: China (Mainland) | I94: Guotai Junan Securities Co Ltd | J94: Financials | K94: Brokerage | L94: China (Mainland) | O94: Completed | P94: China (Mainland) | Q94: Disclosed Dollar Value Deal | V94: =IF(ISNUMBER(S94), "Keep", "Remove") -> Remove
A95: 2625282040 | B95: Tue Mar 11 2014 00:00:00 GMT+0000 (Greenwich Mean Time) | C95: Tue Mar 11 2014 00:00:00 GMT+0000 (Greenwich Mean Time) | D95: 146.96158 | E95: Nanjing Lifang Real Estate Co Ltd | F95: Real Estate | G95: Other Real Estate | H95: China (Mainland) | I95: Yuanying Group Co Ltd | J95: Real Estate | K95: Other Real Estate | L95: Hong Kong | O95: Completed | P95: China (Mainland) | Q95: Disclosed Dollar Value Deal | V95: =IF(ISNUMBER(S95), "Keep", "Remove") -> Remove
A96: 2622602040 | B96: Tue Mar 11 2014 00:00:00 GMT+0000 (Greenwich Mean Time) | C96: Thu Mar 27 2014 00:00:00 GMT+0000 (Greenwich Mean Time) | D96: 1000.46 | E96: OOO Burneftegaz | F96: Energy and Power | G96: Oil & Gas | H96: Russia | I96: OAO Aktsionernaya Neftyanaya Kompaniya Bashneft | J96: Energy and Power | K96: Oil & Gas | L96: Russia | M96: Barclays PLC | N96: Sberbank CIB|Ernst & Young LLP | O96: Completed | P96: Russia | Q96: Disclosed Dollar Value Deal | V96: =IF(ISNUMBER(S96), "Keep", "Remove") -> Remove
A97: 2618968040 | B97: Tue Mar 11 2014 00:00:00 GMT+0000 (Greenwich Mean Time) | C97: Tue Mar 11 2014 00:00:00 GMT+0000 (Greenwich Mean Time) | D97: 353.3927 | E97: SAAG Investimentos SA | F97: Financials | G97: Other Financials | H97: Brazil | I97: Fundo de Investimento em Participacoes Melbourne | J97: Financials | K97: Other Financials | L97: Brazil | M97: Rothschild & Co | N97: Santander Corp & Invest Bkg | O97: Completed | P97: Brazil | Q97: Disclosed Dollar Value Deal | V97: =IF(ISNUMBER(S97), "Keep", "Remove") -> Remove
A98: 2628619040 | B98: Wed Mar 12 2014 00:00:00 GMT+0000 (Greenwich Mean Time) | C98: Fri Apr 18 2014 00:00:00 GMT+0100 (British Summer Time) | D98: 80.40617 | E98: Wujiang Xinmin Chemical Fibre Co Ltd | F98: Consumer Staples | G98: Textiles & Apparel | H98: China (Mainland) | I98: Dongfang Hengxin Capital Holding Group Co Ltd | J98: Financials | K98: Other Financials | L98: China (Mainland) | O98: Completed | P98: China (Mainland) | Q98: Disclosed Dollar Value Deal | V98: =IF(ISNUMBER(S98), "Keep", "Remove") -> Remove
A99: 2618405040 | B99: Thu Mar 13 2014 00:00:00 GMT+0000 (Greenwich Mean Time) | C99: Thu Mar 13 2014 00:00:00 GMT+0000 (Greenwich Mean Time) | D99: 63.462515 | E99: Caxuana Ltda-Forest Assets | F99: Materials | G99: Paper & Forest Products | H99: Brazil | I99: Duratex SA | J99: Materials | K99: Construction Materials | L99: Brazil | O99: Completed | P99: Brazil | Q99: Disclosed Dollar Value Deal | V99: =IF(ISNUMBER(S99), "Keep", "Remove") -> Remove
A100: 2618362040 | B100: Thu Mar 13 2014 00:00:00 GMT+0000 (Greenwich Mean Time) | C100: Thu Mar 13 2014 00:00:00 GMT+0000 (Greenwich Mean Time) | D100: 290.78863 | E100: CTIS Tecnologia SA | F100: High Technology | G100: IT Consulting & Services | H100: Brazil | I100: Sonda SA | J100: High Technology | K100: IT Consulting & Services | L100: Chile | M100: Banco Santander Brasil SA|Clairfield International | O100: Completed | P100: Brazil | Q100: Disclosed Dollar Value Deal | V100: =IF(ISNUMBER(S100), "Keep", "Remove") -> Remove
...

Sheet RISKSHEET
A1: Helper | B1: Country | C1: YEAR | D1: RULE OF LAW | E1: POLITICAL RISK | F1: GOVT EFFECTIVENESS | G1: Helper
A2: =B2&C2 -> china2014 | B2: china | C2: 2014 | D2: -0.39605319 | E2: -0.52258402 | F2: -0.0051206895 | G2: china2014
A3: =B3&C3 -> china2015 | B3: china | C3: 2015 | D3: -0.4084557 | E3: -0.55255967 | F3: 0.41687563 | G3: china2015
A4: =B4&C4 -> china2016 | B4: china | C4: 2016 | D4: -0.32396874 | E4: -0.50222135 | F4: 0.41687563 | G4: china2016
A5: =B5&C5 -> china2017 | B5: china | C5: 2017 | D5: -0.25517809 | E5: -0.2325581 | F5: 0.41687563 | G5: china2017
A6: =B6&C6 -> china2018 | B6: china | C6: 2018 | D6: -0.1864792 | E6: -0.29857248 | F6: 0.49667844 | G6: china2018
A7: =B7&C7 -> china2019 | B7: china | C7: 2019 | D7: -0.26168153 | E7: -0.25978068 | F7: 0.54486251 | G7: china2019
A8: =B8&C8 -> china2020 | B8: china | C8: 2020 | D8: -0.1025051 | E8: -0.47412786 | F8: 0.64397168 | G8: china2020
A9: =B9&C9 -> china2021 | B9: china | C9: 2021 | D9: 0.010268886 | E9: -0.51646286 | F9: 0.80791163 | G9: china2021
A10: =B10&C10 -> china2022 | B10: china | C10: 2022 | D10: -0.042176291 | E10: -0.45127672 | F10: 0.49421254 | G10: china2022
A11: =B11&C11 -> china2023 | B11: china | C11: 2023 | D11: -0.040129971 | E11: -0.51309705 | F11: 0.67901403 | G11: china2023
A12: =B12&C12 -> Brazil2014 | B12: Brazil | C12: 2014 | D12: -0.05296576 | E12: -0.070290133 | F12: -0.11903097 | G12: Brazil2014
A13: =B13&C13 -> Brazil2015 | B13: Brazil | C13: 2015 | D13: -0.18733296 | E13: -0.33186445 | F13: -0.31714061 | G13: Brazil2015
... A51: =B51&C51 -> South Africa2023 | B51: South Africa | C51: 2023 | D51: 0.086235084 | E51: -0.66564202 | F51: -0.25694668 | G51: South Africa2023

Sheet CREDITRATING
A1: COUNTRY | B1: DATE | C1: with month Year | D1: Rating (Moody’s / S&P / Fitch) | E1: CONVERTED | F1: Rating (Converted Score) | G1: YEAR | H1: Helper key | I1: Helper key
A2: Brazil | B2: =DATE(RIGHT(C2,4), MONTH(1 & LEFT(C2,3)), MID(C2,5,2)) -> 41891 | C2: Sep 09 2014 | D2: Baa2 | E2: =IF(OR(D2="Ba1", D2="BB (high)"), "BB+", IF(OR(D2="Ba2", D2="BB"), "BB", IF(OR(D2="Ba3", D2="BB (low)"), "BB-", IF(OR(D2="Baa3", D2="BBB (low)"), "BBB-", IF(D2="Baa2", "BBB", IF(D2="Baa1", "BBB+", IF(D2="BB+", "BB+", IF(D2="BB", "BB", IF(D2="BB-", "BB-", IF(D2="BBB-", "BBB-", IF(D2="BBB", "BBB", IF(D2="BBB+", "BBB+", D2)))))))))))) -> BBB | F2: {=IF(E2="NR","",_xlfn.IFS( E2="AAA",1, E2="AA+",2, E2="AA",3, E2="AA-",4, E2="A+",5, E2="A",6, E2="A-",7, E2="BBB+",8, E2="BBB",9, E2="BBB-",10, E2="BB+",11, E2="BB",12, E2="BB-",13, E2="B+",14, E2="B",15, E2="B-",16, E2="CCC+",17, E2="CCC",18, E2="CC",19, E2="C",20, E2="D",21 ))} -> 9 | G2: =RIGHT(C2, 4) -> 2014 | H2: =PROPER(A2) & G2 -> Brazil2014 | I2: Brazil2014
A3: Brazil | B3: =DATE(RIGHT(C3,4), MONTH(1 & LEFT(C3,3)), MID(C3,5,2)) -> 42347 | C3: Dec 09 2015 | D3: Baa3 | E3: =IF(OR(D3="Ba1", D3="BB (high)"), "BB+", IF(OR(D3="Ba2", D3="BB"), "BB", IF(OR(D3="Ba3", D3="BB (low)"), "BB-", IF(OR(D3="Baa3", D3="BBB (low)"), "BBB-", IF(D3="Baa2", "BBB", IF(D3="Baa1", "BBB+", IF(D3="BB+", "BB+", IF(D3="BB", "BB", IF(D3="BB-", "BB-", IF(D3="BBB-", "BBB-", IF(D3="BBB", "BBB", IF(D3="BBB+", "BBB+", D3)))))))))))) -> BBB- | F3: {=IF(E3="NR","",_xlfn.IFS( E3="AAA",1, E3="AA+",2, E3="AA",3, E3="AA-",4, E3="A+",5, E3="A",6, E3="A-",7, E3="BBB+",8, E3="BBB",9, E3="BBB-",10, E3="BB+",11, E3="BB",12, E3="BB-",13, E3="B+",14, E3="B",15, E3="B-",16, E3="CCC+",17, E3="CCC",18, E3="CC",19, E3="C",20, E3="D",21 ))} -> 10 | G3: =RIGHT(C3, 4) -> 2015 | H3: =PROPER(A3) & G3 -> Brazil2015 | I3: Brazil2015
A4: Brazil | B4: =DATE(RIGHT(C4,4), MONTH(1 & LEFT(C4,3)), MID(C4,5,2)) -> 42583 | C4: Aug 01 2016 | D4: BB | E4: =IF(OR(D4="Ba1", D4="BB (high)"), "BB+", IF(OR(D4="Ba2", D4="BB"), "BB", IF(OR(D4="Ba3", D4="BB (low)"), "BB-", IF(OR(D4="Baa3", D4="BBB (low)"), "BBB-", IF(D4="Baa2", "BBB", IF(D4="Baa1", "BBB+", IF(D4="BB+", "BB+", IF(D4="BB", "BB", IF(D4="BB-", "BB-", IF(D4="BBB-", "BBB-", IF(D4="BBB", "BBB", IF(D4="BBB+", "BBB+", D4)))))))))))) -> BB | F4: {=IF(E4="NR","",_xlfn.IFS( E4="AAA",1, E4="AA+",2, E4="AA",3, E4="AA-",4, E4="A+",5, E4="A",6, E4="A-",7, E4="BBB+",8, E4="BBB",9, E4="BBB-",10, E4="BB+",11, E4="BB",12, E4="BB-",13, E4="B+",14, E4="B",15, E4="B-",16, E4="CCC+",17, E4="CCC",18, E4="CC",19, E4="C",20, E4="D",21 ))} -> 12 | G4: =RIGHT(C4, 4) -> 2016 | H4: =PROPER(A4) & G4 -> Brazil2016 | I4: Brazil2016
A5: Brazil | B5: =DATE(RIGHT(C5,4), MONTH(1 & LEFT(C5,3)), MID(C5,5,2)) -> 42962 | C5: Aug 15 2017 | D5: BB | E5: =IF(OR(D5="Ba1", D5="BB (high)"), "BB+", IF(OR(D5="Ba2", D5="BB"), "BB", IF(OR(D5="Ba3", D5="BB (low)"), "BB-", IF(OR(D5="Baa3", D5="BBB (low)"), "BBB-", IF(D5="Baa2", "BBB", IF(D5="Baa1", "BBB+", IF(D5="BB+", "BB+", IF(D5="BB", "BB", IF(D5="BB-", "BB-", IF(D5="BBB-", "BBB-", IF(D5="BBB", "BBB", IF(D5="BBB+", "BBB+", D5)))))))))))) -> BB | F5: {=IF(E5="NR","",_xlfn.IFS( E5="AAA",1, E5="AA+",2, E5="AA",3, E5="AA-",4, E5="A+",5, E5="A",6, E5="A-",7, E5="BBB+",8, E5="BBB",9, E5="BBB-",10, E5="BB+",11, E5="BB",12, E5="BB-",13, E5="B+",14, E5="B",15, E5="B-",16, E5="CCC+",17, E5="CCC",18, E5="CC",19, E5="C",20, E5="D",21 ))} -> 12 | G5: =RIGHT(C5, 4) -> 2017 | H5: =PROPER(A5) & G5 -> Brazil2017 | I5: Brazil2017
A6: Brazil | B6: =DATE(RIGHT(C6,4), MONTH(1 & LEFT(C6,3)), MID(C6,5,2)) -> 43199 | C6: Apr 09 2018 | D6: Ba2 | E6: =IF(OR(D6="Ba1", D6="BB (high)"), "BB+", IF(OR(D6="Ba2", D6="BB"), "BB", IF(OR(D6="Ba3", D6="BB (low)"), "BB-", IF(OR(D6="Baa3", D6="BBB (low)"), "BBB-", IF(D6="Baa2", "BBB", IF(D6="Baa1", "BBB+", IF(D6="BB+", "BB+", IF(D6="BB", "BB", IF(D6="BB-", "BB-", IF(D6="BBB-", "BBB-", IF(D6="BBB", "BBB", IF(D6="BBB+", "BBB+", D6)))))))))))) -> BB | F6: {=IF(E6="NR","",_xlfn.IFS( E6="AAA",1, E6="AA+",2, E6="AA",3, E6="AA-",4, E6="A+",5, E6="A",6, E6="A-",7, E6="BBB+",8, E6="BBB",9, E6="BBB-",10, E6="BB+",11, E6="BB",12, E6="BB-",13, E6="B+",14, E6="B",15, E6="B-",16, E6="CCC+",17, E6="CCC",18, E6="CC",19, E6="C",20, E6="D",21 ))} -> 12 | G6: =RIGHT(C6, 4) -> 2018 | H6: =PROPER(A6) & G6 -> Brazil2018 | I6: Brazil2018
A7: Brazil | B7: =DATE(RIGHT(C7,4), MONTH(1 & LEFT(C7,3)), MID(C7,5,2)) -> 43810 | C7: Dec 11 2019 | D7: BB- | E7: =IF(OR(D7="Ba1", D7="BB (high)"), "BB+", IF(OR(D7="Ba2", D7="BB"), "BB", IF(OR(D7="Ba3", D7="BB (low)"), "BB-", IF(OR(D7="Baa3", D7="BBB (low)"), "BBB-", IF(D7="Baa2", "BBB", IF(D7="Baa1", "BBB+", IF(D7="BB+", "BB+", IF(D7="BB", "BB", IF(D7="BB-", "BB-", IF(D7="BBB-", "BBB-", IF(D7="BBB", "BBB", IF(D7="BBB+", "BBB+", D7)))))))))))) -> BB- | F7: {=IF(E7="NR","",_xlfn.IFS( E7="AAA",1, E7="AA+",2, E7="AA",3, E7="AA-",4, E7="A+",5, E7="A",6, E7="A-",7, E7="BBB+",8, E7="BBB",9, E7="BBB-",10, E7="BB+",11, E7="BB",12, E7="BB-",13, E7="B+",14, E7="B",15, E7="B-",16, E7="CCC+",17, E7="CCC",18, E7="CC",19, E7="C",20, E7="D",21 ))} -> 13 | G7: =RIGHT(C7, 4) -> 2019 | H7: =PROPER(A7) & G7 -> Brazil2019 | I7: Brazil2019
A8: Brazil | B8: =DATE(RIGHT(C8,4), MONTH(1 & LEFT(C8,3)), MID(C8,5,2)) -> 43927 | C8: Apr 06 2020 | D8: BB- | E8: =IF(OR(D8="Ba1", D8="BB (high)"), "BB+", IF(OR(D8="Ba2", D8="BB"), "BB", IF(OR(D8="Ba3", D8="BB (low)"), "BB-", IF(OR(D8="Baa3", D8="BBB (low)"), "BBB-", IF(D8="Baa2", "BBB", IF(D8="Baa1", "BBB+", IF(D8="BB+", "BB+", IF(D8="BB", "BB", IF(D8="BB-", "BB-", IF(D8="BBB-", "BBB-", IF(D8="BBB", "BBB", IF(D8="BBB+", "BBB+", D8)))))))))))) -> BB- | F8: {=IF(E8="NR","",_xlfn.IFS( E8="AAA",1, E8="AA+",2, E8="AA",3, E8="AA-",4, E8="A+",5, E8="A",6, E8="A-",7, E8="BBB+",8, E8="BBB",9, E8="BBB-",10, E8="BB+",11, E8="BB",12, E8="BB-",13, E8="B+",14, E8="B",15, E8="B-",16, E8="CCC+",17, E8="CCC",18, E8="CC",19, E8="C",20, E8="D",21 ))} -> 13 | G8: =RIGHT(C8, 4) -> 2020 | H8: =PROPER(A8) & G8 -> Brazil2020 | I8: Brazil2020
A9: Brazil | B9: =DATE(RIGHT(C9,4), MONTH(1 & LEFT(C9,3)), MID(C9,5,2)) -> 44292 | C9: Apr 06 2021 | D9: BB- | E9: =IF(OR(D9="Ba1", D9="BB (high)"), "BB+", IF(OR(D9="Ba2", D9="BB"), "BB", IF(OR(D9="Ba3", D9="BB (low)"), "BB-", IF(OR(D9="Baa3", D9="BBB (low)"), "BBB-", IF(D9="Baa2", "BBB", IF(D9="Baa1", "BBB+", IF(D9="BB+", "BB+", IF(D9="BB", "BB", IF(D9="BB-", "BB-", IF(D9="BBB-", "BBB-", IF(D9="BBB", "BBB", IF(D9="BBB+", "BBB+", D9)))))))))))) -> BB- | F9: {=IF(E9="NR","",_xlfn.IFS( E9="AAA",1, E9="AA+",2, E9="AA",3, E9="AA-",4, E9="A+",5, E9="A",6, E9="A-",7, E9="BBB+",8, E9="BBB",9, E9="BBB-",10, E9="BB+",11, E9="BB",12, E9="BB-",13, E9="B+",14, E9="B",15, E9="B-",16, E9="CCC+",17, E9="CCC",18, E9="CC",19, E9="C",20, E9="D",21 ))} -> 13 | G9: =RIGHT(C9, 4) -> 2021 | H9: =PROPER(A9) & G9 -> Brazil2021 | I9: Brazil2021
A10: Brazil | B10: =DATE(RIGHT(C10,4), MONTH(1 & LEFT(C10,3)), MID(C10,5,2)) -> 44657 | C10: Apr 06 2022 | D10: BB | E10: =IF(OR(D10="Ba1", D10="BB (high)"), "BB+", IF(OR(D10="Ba2", D10="BB"), "BB", IF(OR(D10="Ba3", D10="BB (low)"), "BB-", IF(OR(D10="Baa3", D10="BBB (low)"), "BBB-", IF(D10="Baa2", "BBB", IF(D10="Baa1", "BBB+", IF(D10="BB+", "BB+", IF(D10="BB", "BB", IF(D10="BB-", "BB-", IF(D10="BBB-", "BBB-", IF(D10="BBB", "BBB", IF(D10="BBB+", "BBB+", D10)))))))))))) -> BB | F10: {=IF(E10="NR","",_xlfn.IFS( E10="AAA",1, E10="AA+",2, E10="AA",3, E10="AA-",4, E10="A+",5, E10="A",6, E10="A-",7, E10="BBB+",8, E10="BBB",9, E10="BBB-",10, E10="BB+",11, E10="BB",12, E10="BB-",13, E10="B+",14, E10="B",15, E10="B-",16, E10="CCC+",17, E10="CCC",18, E10="CC",19, E10="C",20, E10="D",21 ))} -> 12 | G10: =RIGHT(C10, 4) -> 2022 | H10: =PROPER(A10) & G10 -> Brazil2022 | I10: Brazil2022
A11: Brazil | B11: =DATE(RIGHT(C11,4), MONTH(1 & LEFT(C11,3)), MID(C11,5,2)) -> 45279 | C11: Dec 19 2023 | D11: BB | E11: =IF(OR(D11="Ba1", D11="BB (high)"), "BB+", IF(OR(D11="Ba2", D11="BB"), "BB", IF(OR(D11="Ba3", D11="BB (low)"), "BB-", IF(OR(D11="Baa3", D11="BBB (low)"), "BBB-", IF(D11="Baa2", "BBB", IF(D11="Baa1", "BBB+", IF(D11="BB+", "BB+", IF(D11="BB", "BB", IF(D11="BB-", "BB-", IF(D11="BBB-", "BBB-", IF(D11="BBB", "BBB", IF(D11="BBB+", "BBB+", D11)))))))))))) -> BB | F11: {=IF(E11="NR","",_xlfn.IFS( E11="AAA",1, E11="AA+",2, E11="AA",3, E11="AA-",4, E11="A+",5, E11="A",6, E11="A-",7, E11="BBB+",8, E11="BBB",9, E11="BBB-",10, E11="BB+",11, E11="BB",12, E11="BB-",13, E11="B+",14, E11="B",15, E11="B-",16, E11="CCC+",17, E11="CCC",18, E11="CC",19, E11="C",20, E11="D",21 ))} -> 12 | G11: =RIGHT(C11, 4) -> 2023 | H11: =PROPER(A11) & G11 -> Brazil2023 | I11: Brazil2023
A12: Brazil | B12: =DATE(RIGHT(C12,4), MONTH(1 & LEFT(C12,3)), MID(C12,5,2)) -> 45566 | C12: Oct 01 2024 | D12: Ba1 | E12: =IF(OR(D12="Ba1", D12="BB (high)"), "BB+", IF(OR(D12="Ba2", D12="BB"), "BB", IF(OR(D12="Ba3", D12="BB (low)"), "BB-", IF(OR(D12="Baa3", D12="BBB (low)"), "BBB-", IF(D12="Baa2", "BBB", IF(D12="Baa1", "BBB+", IF(D12="BB+", "BB+", IF(D12="BB", "BB", IF(D12="BB-", "BB-", IF(D12="BBB-", "BBB-", IF(D12="BBB", "BBB", IF(D12="BBB+", "BBB+", D12)))))))))))) -> BB+ | F12: {=IF(E12="NR","",_xlfn.IFS( E12="AAA",1, E12="AA+",2, E12="AA",3, E12="AA-",4, E12="A+",5, E12="A",6, E12="A-",7, E12="BBB+",8, E12="BBB",9, E12="BBB-",10, E12="BB+",11, E12="BB",12, E12="BB-",13, E12="B+",14, E12="B",15, E12="B-",16, E12="CCC+",17, E12="CCC",18, E12="CC",19, E12="C",20, E12="D",21 ))} -> 11 | G12: =RIGHT(C12, 4) -> 2024 | H12: =PROPER(A12) & G12 -> Brazil2024 | I12: Brazil2024
A13: china | B13: =DATE(RIGHT(C13,4), MONTH(1 & LEFT(C13,3)), MID(C13,5,2)) -> 41911 | C13: Sep 29 2014 | D13: A (high) | E13: A+ | F13: 5 | G13: =RIGHT(C13, 4) -> 2014 | H13: =PROPER(A13) & G13 -> China2014 | I13: China2014
A14: china | B14: =DATE(RIGHT(C14,4), MONTH(1 & LEFT(C14,3)), MID(C14,5,2)) -> 42276 | C14: Sep 29 2015 | D14: A (high) | E14: A+ | F14: 5 | G14: =RIGHT(C14, 4) -> 2015 | H14: =PROPER(A14) & G14 -> China2015 | I14: China2015
A15: china | B15: =DATE(RIGHT(C15,4), MONTH(1 & LEFT(C15,3)), MID(C15,5,2)) -> 42460 | C15: Mar 31 2016 | D15: AA- | E15: AA- | F15: 4 | G15: =RIGHT(C15, 4) -> 2016 | H15: =PROPER(A15) & G15 -> China2016 | I15: China2016
A16: china | B16: =DATE(RIGHT(C16,4), MONTH(1 & LEFT(C16,3)), MID(C16,5,2)) -> 42999 | C16: Sep 21 2017 | D16: A+ | E16: A+ | F16: 5 | G16: =RIGHT(C16, 4) -> 2017 | H16: =PROPER(A16) & G16 -> China2017 | I16: China2017
A17: china | B17: =DATE(RIGHT(C17,4), MONTH(1 & LEFT(C17,3)), MID(C17,5,2)) -> 43364 | C17: Sep 21 2018 | D17: A+ | E17: A+ | F17: 5 | G17: =RIGHT(C17, 4) -> 2018 | H17: =PROPER(A17) & G17 -> China2018 | I17: China2018
A18: china | B18: =DATE(RIGHT(C18,4), MONTH(1 & LEFT(C18,3)), MID(C18,5,2)) -> 43545 | C18: Mar 21 2019 | D18: A (high) | E18: A+ | F18: 5 | G18: =RIGHT(C18, 4) -> 2019 | H18: =PROPER(A18) & G18 -> China2019 | I18: China2019
A19: china | B19: =DATE(RIGHT(C19,4), MONTH(1 & LEFT(C19,3)), MID(C19,5,2)) -> 44148 | C19: Nov 13 2020 | D19: A (high) | E19: A+ | F19: 5 | G19: =RIGHT(C19, 4) -> 2020 | H19: =PROPER(A19) & G19 -> China2020 | I19: China2020
A20: china | B20: =DATE(RIGHT(C20,4), MONTH(1 & LEFT(C20,3)), MID(C20,5,2)) -> 44513 | C20: Nov 13 2021 | D20: A (high) | E20: A+ | F20: 5 | G20: =RIGHT(C20, 4) -> 2021 | H20: =PROPER(A20) & G20 -> China2021 | I20: China2021
A21: china | B21: =DATE(RIGHT(C21,4), MONTH(1 & LEFT(C21,3)), MID(C21,5,2)) -> 44875 | C21: Nov 10 2022 | D21: A (high) | E21: A+ | F21: 5 | G21: =RIGHT(C21, 4) -> 2022 | H21: =PROPER(A21) & G21 -> China2022 | I21: China2022
A22: china | B22: =DATE(RIGHT(C22,4), MONTH(1 & LEFT(C22,3)), MID(C22,5,2)) -> 45265 | C22: Dec 05 2023 | D22: A1 | E22: A+ | F22: 5 | G22: =RIGHT(C22, 4) -> 2023 | H22: =PROPER(A22) & G22 -> China2023 | I22: China2023
A23: china | B23: =DATE(RIGHT(C23,4), MONTH(1 & LEFT(C23,3)), MID(C23,5,2)) -> 45631 | C23: Dec 05 2024 | D23: A1 | E23: A+ | F23: 5 | G23: =RIGHT(C23, 4) -> 2024 | H23: =PROPER(A23) & G23 -> China2024 | I23: China2024
A24: india | B24: =DATE(RIGHT(C24,4), MONTH(1 & LEFT(C24,3)), MID(C24,5,2)) -> 41948 | C24: Nov 05 2014 | D24: BBB (low) | E24: BBB- | F24: 10 | G24: =RIGHT(C24, 4) -> 2014 | H24: =PROPER(A24) & G24 -> India2014 | I24: India2014
... A43: Russia | B43: =DATE(RIGHT(C43,4), MONTH(1 & LEFT(C43,3)), MID(C43,5,2)) -> 44235 | C43: Feb 08 2021 | D43: Baa3 | E43: BBB- | F43: 10 | G43: =RIGHT(C43, 4) -> 2021 | H43: =PROPER(A43) & G43 -> Russia2021 | I43: Russia2021
A44: Russia | B44: =DATE(RIGHT(C44,4), MONTH(1 & LEFT(C44,3)), MID(C44,5,2)) -> 44659 | C44: Apr 08 2022 | D44: NR | E44: NR | G44: =RIGHT(C44, 4) -> 2022 | H44: =PROPER(A44) & G44 -> Russia2022 | I44: Russia2022
A45: South Africa | B45: =DATE(RIGHT(C45,4), MONTH(1 & LEFT(C45,3)), MID(C45,5,2)) -> 41949 | C45: Nov 06 2014 | D45: Baa2 | E45: BB | F45: 12 | G45: =RIGHT(C45, 4) -> 2014 | H45: =PROPER(A45) & G45 -> South Africa2014 | I45: South Africa2014
A46: South Africa | B46: =DATE(RIGHT(C46,4), MONTH(1 & LEFT(C46,3)), MID(C46,5,2)) -> 42342 | C46: Dec 04 2015 | D46: BBB- | E46: BBB- | F46: 10 | G46: =RIGHT(C46, 4) -> 2015 | H46: =PROPER(A46) & G46 -> South Africa2015 | I46: South Africa2015
A47: South Africa | B47: =DATE(RIGHT(C47,4), MONTH(1 & LEFT(C47,3)), MID(C47,5,2)) -> 42496 | C47: May 06 2016 | D47: Baa2 | E47: BB | F47: 12 | G47: =RIGHT(C47, 4) -> 2016 | H47: =PROPER(A47) & G47 -> South Africa2016 | I47: South Africa2016
A48: South Africa | B48: =DATE(RIGHT(C48,4), MONTH(1 & LEFT(C48,3)), MID(C48,5,2)) -> 43063 | C48: Nov 24 2017 | D48: BB | E48: BB | F48: 12 | G48: =RIGHT(C48, 4) -> 2017 | H48: =PROPER(A48) & G48 -> South Africa2017 | I48: South Africa2017
A49: South Africa | B49: =DATE(RIGHT(C49,4), MONTH(1 & LEFT(C49,3)), MID(C49,5,2)) -> 43182 | C49: Mar 23 2018 | D49: Baa3 | E49: BBB- | F49: 10 | G49: =RIGHT(C49, 4) -> 2018 | H49: =PROPER(A49) & G49 -> South Africa2018 | I49: South Africa2018
A50: South Africa | B50: =DATE(RIGHT(C50,4), MONTH(1 & LEFT(C50,3)), MID(C50,5,2)) -> 43791 | C50: Nov 22 2019 | D50: BB | E50: BB | F50: 12 | G50: =RIGHT(C50, 4) -> 2019 | H50: =PROPER(A50) & G50 -> South Africa2019 | I50: South Africa2019
A51: South Africa | B51: =DATE(RIGHT(C51,4), MONTH(1 & LEFT(C51,3)), MID(C51,5,2)) -> 44155 | C51: Nov 20 2020 | D51: Ba2 | E51: BB | F51: 12 | G51: =RIGHT(C51, 4) -> 2020 | H51: =PROPER(A51) & G51 -> South Africa2020 | I51: South Africa2020
A52: South Africa | B52: =DATE(RIGHT(C52,4), MONTH(1 & LEFT(C52,3)), MID(C52,5,2)) -> 44520 | C52: Nov 20 2021 | D52: Ba2 | E52: BB | F52: 12 | G52: =RIGHT(C52, 4) -> 2021 | H52: =PROPER(A52) & G52 -> South Africa2021 | I52: South Africa2021
A53: South Africa | B53: =DATE(RIGHT(C53,4), MONTH(1 & LEFT(C53,3)), MID(C53,5,2)) -> 44701 | C53: May 20 2022 | D53: BB- | E53: BB- | F53: 13 | G53: =RIGHT(C53, 4) -> 2022 | H53: =PROPER(A53) & G53 -> South Africa2022 | I53: South Africa2022
A54: South Africa | B54: =DATE(RIGHT(C54,4), MONTH(1 & LEFT(C54,3)), MID(C54,5,2)) -> 44993 | C54: Mar 08 2023 | D54: BB- | E54: BB- | F54: 13 | G54: =RIGHT(C54, 4) -> 2023 | H54: =PROPER(A54) & G54 -> South Africa2023 | I54: South Africa2023
A55: South Africa | B55: =DATE(RIGHT(C55,4), MONTH(1 & LEFT(C55,3)), MID(C55,5,2)) -> 45611 | C55: Nov 15 2024 | D55: BB- | E55: BB- | F55: 13 | G55: =RIGHT(C55, 4) -> 2024 | H55: =PROPER(A55) & G55 -> South Africa2024 | I55: South Africa2024

Sheet Sheet7
B4: | Variable | Coefficient | Robust Std. Error | t | P>|t| | 95% Confidence Interval |
B5: |------------------------|-------------|-------------------|-------|-----|--------------------------|
B6: | Rule of Law (z_rol) | -528.881 | 426.110 | -1.24 | 0.216 | -1368.664 to 310.899 |
B7: | Political Risk (z_polrisk) | 394.700 | 333.268 | 1.18 | 0.238 | -262.106 to 1051.506 |
B8: | Gov. Effectiveness (z_govteff) | -155.735 | 179.750 | -0.87 | 0.387 | -509.988 to 198.518 |
B9: | Credit Score (z_cr_score) | -238.321 | 219.020 | -1.09 | 0.278 | -669.967 to 193.324 |
B10: | _cons | -379.657 | 462.851 | -0.82 | 0.413 | -1291.847 to 532.532 |
